digital_circuits/sequential_circuits/counter/synchronous_counters/up_counter/mod_8/rtl/D.v
module D (
    input clk,
    input en,
    input areset_n,
    input d,
    output reg q
);

    always @(posedge clk, negedge areset_n) begin
        if(!areset_n) begin
            q <= 1'b0;
        end
        else if(en) begin
            q <= d;
        end
        else begin
            q <= q;
        end
    end

endmodule

digital_circuits/sequential_circuits/counter/synchronous_counters/up_down_counter/mod_8/rtl/mod_8.v
module mod_8(
    input clk,
    input en,
    input areset_n,
    input up_down,
    output [2:0] out
);

    wire a,b,c;

    wire a_in, b_in, c_in;

    assign a_in = (~a & ~b & ~c & ~up_down) | (~a & b & c & up_down) | (a & b & ~c) | (a & ~b & up_down) | (a & c & ~up_down);
    assign b_in = ~(b ^ (c ^ up_down));
    assign c_in = ~c;

    assign out = {a,b,c};

    D dff2(
        .clk(clk),
        .en(en),
        .areset_n(areset_n),
        .d(a_in),
        .q(a)
    );

    D dff1(
        .clk(clk),
        .en(en),
        .areset_n(areset_n),
        .d(b_in),
        .q(b)
    );

    D dff0(
        .clk(clk),
        .en(en),
        .areset_n(areset_n),
        .d(c_in),
        .q(c)
    );


endmodule

digital_circuits/sequential_circuits/counter/asynchronous_counters/up_down_counter/mod_8/tb/tb_mod_8.v
`timescale 1ns/1ps

module tb_mod_8;
    reg clk;
    reg en;
    reg areset_n;
    reg up_down;
    wire [2:0] out;

    mod_8 dut(
        .clk(clk),
        .en(en),
        .areset_n(areset_n),
        .up_down(up_down),
        .out(out)
    );

    initial begin
        $dumpfile("waves/dump.vcd");
        $dumpvars(0,tb_mod_8);
    end

    initial begin
        clk = 0;
        forever #5 clk = ~clk;
    end

    initial begin
        en=0;
        areset_n=0;
        up_down=0;
    end


    task check;
        input reg in;
        begin
            up_down = in;
            #1;
            repeat(10) begin
                @(negedge clk)
                $display("en = %b | areset_n = %b | up_down = %b | out = %h", en,areset_n,up_down,out);
            end
        end
    endtask

    initial begin
        #6 en=1;
        #6 areset_n=1;
        #8;
        check(1);
        check(0);
        #20 $finish;
    end
endmodule

digital_circuits/sequential_circuits/counter/synchronous_counters/up_down_counter/mod_8/waves/dump.vcd
$date
	Thu Sep 17 05:34:03 2026
$end
$version
	Icarus Verilog
$end
$timescale
	1ps
$end
$scope module tb_mod_8 $end
$var wire 3 ! out [2:0] $end
$var reg 1 " areset_n $end
$var reg 1 # clk $end
$var reg 1 $ en $end
$var reg 1 % up_down $end
$scope module dut $end
$var wire 1 & a_in $end
$var wire 1 " areset_n $end
$var wire 1 ' b_in $end
$var wire 1 ( c_in $end
$var wire 1 # clk $end
$var wire 1 $ en $end
$var wire 1 % up_down $end
$var wire 3 ) out [2:0] $end
$var wire 1 * c $end
$var wire 1 + b $end
$var wire 1 , a $end
$scope module dff0 $end
$var wire 1 " areset_n $end
$var wire 1 # clk $end
$var wire 1 ( d $end
$var wire 1 $ en $end
$var reg 1 * q $end
$upscope $end
$scope module dff1 $end
$var wire 1 " areset_n $end
$var wire 1 # clk $end
$var wire 1 ' d $end
$var wire 1 $ en $end
$var reg 1 + q $end
$upscope $end
$scope module dff2 $end
$var wire 1 " areset_n $end
$var wire 1 # clk $end
$var wire 1 & d $end
$var wire 1 $ en $end
$var reg 1 , q $end
$upscope $end
$upscope $end
$scope task check $end
$var reg 1 - in $end
$upscope $end
$upscope $end
$enddefinitions $end
$comment Show the parameter values. $end
$dumpall
$end
#0
$dumpvars
x-
0,
0+
0*
b0 )
1(
1'
1&
0%
0$
0#
0"
b0 !
$end
#5000
1#
#6000
1$
#10000
0#
#12000
1"
#15000
0(
1,
1+
b111 !
b111 )
1*
1#
#20000
0&
0'
0#
1%
1-
#25000
0'
1(
0*
0+
b0 !
b0 )
0,
1#
#30000
0#
#35000
1'
0(
b1 !
b1 )
1*
1#
#40000
0#
#45000
1'
1(
0*
b10 !
b10 )
1+
1#
#50000
0#
#55000
1&
0'
0(
b11 !
b11 )
1*
1#
#60000
0#
#65000
0'
1(
0*
0+
b100 !
b100 )
1,
1#
#70000
0#
#75000
1'
0(
b101 !
b101 )
1*
1#
#80000
0#
#85000
1'
1(
0*
b110 !
b110 )
1+
1#
#90000
0#
#95000
0&
0'
0(
b111 !
b111 )
1*
1#
#100000
0#
#105000
0'
1(
0*
0+
b0 !
b0 )
0,
1#
#110000
0#
#115000
1'
0(
b1 !
b1 )
1*
1#
#120000
0'
0%
0-
0#
#125000
1&
1'
1(
b0 !
b0 )
0*
1#
#130000
0#
#135000
0(
1,
1+
b111 !
b111 )
1*
1#
#140000
0#
#145000
0'
1&
1(
b110 !
b110 )
0*
1#
#150000
0#
#155000
0(
0+
b101 !
b101 )
1*
1#
#160000
0#
#165000
1'
0&
1(
b100 !
b100 )
0*
1#
#170000
0#
#175000
0(
0,
1+
b11 !
b11 )
1*
1#
#180000
0#
#185000
0'
1(
b10 !
b10 )
0*
1#
#190000
0#
#195000
0(
0+
b1 !
b1 )
1*
1#
#200000
0#
#205000
1&
1'
1(
b0 !
b0 )
0*
1#
#210000
0#
#215000
0(
1,
1+
b111 !
b111 )
1*
1#
#220000
0#
#225000
0'
1&
1(
b110 !
b110 )
0*
1#
#230000
0#
#235000
0(
0+
b101 !
b101 )
1*
1#
