week2/combinational_circuit/encoder_4to2/rtl/encoder_4to2.v
module encoder_4to2 (
    input wire [3:0] d_in,
    output reg [1:0] d_out,
    output reg valid
);

    always @(*) begin
        // d_out=2'b00;
        // d_out[1] = d_in[2] | d_in[3];
        // d_out[0] = d_in[1] | d_in[3];

        valid = 1'b1;
        case(d_in)
            4'b0001:d_out=2'b00;
            4'b0010:d_out=2'b01;
            4'b0100:d_out=2'b10;
            4'b1000:d_out=2'b11;
            default: begin
                d_out = 2'b00;
                valid = 1'b0;
            end 
        endcase

    end
endmodule

digital_circuits/combinational_circuit/encoder_4to2/tb/tb_encoder_4to2.v
`timescale 1ns/1ps
module tb_encoder_4to2;

    reg [3:0] d_in;
    wire [1:0] d_out;
    wire valid;

    encoder_4to2 dut(
        .d_in(d_in),
        .d_out(d_out),
        .valid(valid)
    );

    initial begin
        $dumpfile("waves/dump.vcd");
        $dumpvars(0,tb_encoder_4to2);
    end

    integer pass=0;
    integer fail=0;

    task check;
        reg [1:0] i,j,k,l;
        reg [1:0] exp_out;
        reg exp_valid;
        begin
            for(i=0;i<2;i=i+1) begin 
                d_in[3] = i;
                for(j=0;j<2;j=j+1) begin 
                    d_in[2] = j;
                    for(k=0;k<2;k=k+1) begin
                        d_in[1] = k;
                        for(l=0;l<2;l=l+1) begin
                            d_in[0] = l;
                            exp_valid=1'b1;
                            case(d_in)
                                4'b0001:exp_out = 2'b00;
                                4'b0010:exp_out = 2'b01;
                                4'b0100:exp_out = 2'b10;
                                4'b1000:exp_out = 2'b11;
                                default: begin
                                    exp_valid = 1'b0;
                                    exp_out = 2'b00;
                                end

                            endcase
                            #10; 
                            if(exp_out === d_out && exp_valid === valid) begin
                                $display("PASS: d_in=%b d_out=%b valid=%b",d_in,d_out,valid);
                                pass=pass+1;
                            end
                            else begin
                                $display("FAIL: d_in=%b d_out=%b valid=%b | exp_out=%b exp_valid=%b",d_in,d_out,valid,exp_out,exp_valid);
                                fail=fail+1;
                            end
                            
                        end
                    end
                end
            end
        end
    
    endtask

    initial begin
        check();

        $display("Test Summary");
        $display("PASS: %d", pass);
        $display("FAIL: %d", fail);
    end


endmodule

week2/combinational_circuit/encoder_4to2/waves/dump.vcd
$date
	Mon Jun  1 07:11:38 2026
$end
$version
	Icarus Verilog
$end
$timescale
	1ps
$end
$scope module tb_encoder_4to2 $end
$var wire 1 ! valid $end
$var wire 2 " d_out [1:0] $end
$var reg 4 # d_in [3:0] $end
$var integer 32 $ fail [31:0] $end
$var integer 32 % pass [31:0] $end
$scope module dut $end
$var wire 4 & d_in [3:0] $end
$var reg 2 ' d_out [1:0] $end
$var reg 1 ! valid $end
$upscope $end
$scope task check $end
$var reg 2 ( exp_out [1:0] $end
$var reg 1 ) exp_valid $end
$var reg 2 * i [1:0] $end
$var reg 2 + j [1:0] $end
$var reg 2 , k [1:0] $end
$var reg 2 - l [1:0] $end
$upscope $end
$upscope $end
$enddefinitions $end
$comment Show the parameter values. $end
$dumpall
$end
#0
$dumpvars
b0 -
b0 ,
b0 +
b0 *
0)
b0 (
b0 '
b0 &
b0 %
b0 $
b0 #
b0 "
0!
$end
#10000
1!
1)
b1 #
b1 &
b1 -
b1 %
#20000
b1 "
b1 '
b1 (
b10 #
b10 &
b1 ,
b0 -
b10 %
#30000
0!
b0 "
b0 '
b0 (
0)
b11 #
b11 &
b1 -
b11 %
#40000
b10 "
b10 '
1!
b10 (
1)
b100 #
b100 &
b1 +
b0 ,
b0 -
b100 %
#50000
0!
b0 "
b0 '
b0 (
0)
b101 #
b101 &
b1 -
b101 %
#60000
0!
0)
b110 #
b110 &
b1 ,
b0 -
b110 %
#70000
0!
0)
b111 #
b111 &
b1 -
b111 %
#80000
b11 "
b11 '
1!
b11 (
1)
b1000 #
b1000 &
b1 *
b0 +
b0 ,
b0 -
b1000 %
#90000
0!
b0 "
b0 '
b0 (
0)
b1001 #
b1001 &
b1 -
b1001 %
#100000
0!
0)
b1010 #
b1010 &
b1 ,
b0 -
b1010 %
#110000
0!
0)
b1011 #
b1011 &
b1 -
b1011 %
#120000
0!
0)
b1100 #
b1100 &
b1 +
b0 ,
b0 -
b1100 %
#130000
0!
0)
b1101 #
b1101 &
b1 -
b1101 %
#140000
0!
0)
b1110 #
b1110 &
b1 ,
b0 -
b1110 %
#150000
0!
0)
b1111 #
b1111 &
b1 -
b1111 %
#160000
b10 *
b10 +
b10 ,
b10 -
b10000 %
