digital_circuits/sequential_circuits/shift_registers/SISO/rtl/D.v
module D (
    input clk,
    input en,
    input areset_n,
    input d,
    output reg q
);

    always @(posedge clk, posedge areset_n) begin
        if(!areset_n) begin
            q <= 1'b0;
        end
        else if(en) begin
            q <= d;
        end
        else begin
            q <= q;
        end
    end

endmodule

digital_circuits/sequential_circuits/shift_registers/SIPO/rtl/SIPO.v
module SIPO (
    input clk,
    input en,
    input areset_n,
    input in,
    output reg [3:0] out
);
    wire [3:0] w;
    
    D dff1(
        .clk(clk),
        .en(en),
        .areset_n(areset_n),
        .d(in),
        .q(w[3])
    );

    D dff2(
        .clk(clk),
        .en(en),
        .areset_n(areset_n),
        .d(w[3]),
        .q(w[2])
    );

    D dff3(
        .clk(clk),
        .en(en),
        .areset_n(areset_n),
        .d(w[2]),
        .q(w[1])
    );

    D dff4(
        .clk(clk),
        .en(en),
        .areset_n(areset_n),
        .d(w[1]),
        .q(w[0])
    );
    
    assign out = w;

endmodule

digital_circuits/sequential_circuits/shift_registers/SIPO/tb/tb_SIPO.v
`timescale 1ns/1ps

module tb_SIPO;
    reg clk;
    reg en;
    reg areset_n;
    reg in;
    wire [3:0] out;

    SIPO dut(
        .clk(clk),
        .en(en),
        .areset_n(areset_n),
        .in(in),
        .out(out)
    );

    initial begin
        $dumpfile("waves/dump.vcd");
        $dumpvars(0,tb_SIPO);
    end

    initial begin
        clk= 1'b0;
        forever #5 clk = ~clk;
    end

    initial begin
        en=0;
        areset_n=0;
        in = 0;
    end

    initial begin
        #10 en=1;
        #5 areset_n=1;

        @(negedge clk) in =1'b1;
        @(negedge clk) in =1'b1;
        @(negedge clk) in =1'b0;
        @(negedge clk) in =1'b1;

        #10 areset_n=0;
        #20 areset_n = 1;

        @(negedge clk) in =1'b1;
        @(negedge clk) in =1'b1;
        
        #10 en = 0;

        @(negedge clk) in =1'b0;

        #10 en = 1;
        
        @(negedge clk) in =1'b1;


        #50 $finish;
    end




endmodule

digital_circuits/sequential_circuits/shift_registers/SIPO/waves/dump.vcd
$date
	Tue Sep 15 05:41:38 2026
$end
$version
	Icarus Verilog
$end
$timescale
	1ps
$end
$scope module tb_SIPO $end
$var wire 4 ! out [3:0] $end
$var reg 1 " areset_n $end
$var reg 1 # clk $end
$var reg 1 $ en $end
$var reg 1 % in $end
$scope module dut $end
$var wire 1 " areset_n $end
$var wire 1 # clk $end
$var wire 1 $ en $end
$var wire 1 % in $end
$var wire 4 & out [3:0] $end
$var wire 4 ' w [3:0] $end
$scope module dff1 $end
$var wire 1 " areset_n $end
$var wire 1 # clk $end
$var wire 1 % d $end
$var wire 1 $ en $end
$var reg 1 ( q $end
$upscope $end
$scope module dff2 $end
$var wire 1 " areset_n $end
$var wire 1 # clk $end
$var wire 1 ) d $end
$var wire 1 $ en $end
$var reg 1 * q $end
$upscope $end
$scope module dff3 $end
$var wire 1 " areset_n $end
$var wire 1 # clk $end
$var wire 1 + d $end
$var wire 1 $ en $end
$var reg 1 , q $end
$upscope $end
$scope module dff4 $end
$var wire 1 " areset_n $end
$var wire 1 # clk $end
$var wire 1 - d $end
$var wire 1 $ en $end
$var reg 1 . q $end
$upscope $end
$upscope $end
$upscope $end
$enddefinitions $end
$comment Show the parameter values. $end
$dumpall
$end
#0
$dumpvars
x.
x-
x,
x+
x*
x)
x(
bx '
bx &
0%
0$
0#
0"
bx !
$end
#5000
0)
0+
0-
0(
0*
0,
b0 !
b0 &
b0 '
0.
1#
#10000
0#
1$
#15000
1#
1"
#20000
1%
0#
#25000
1)
b1000 !
b1000 &
b1000 '
1(
1#
#30000
0#
#35000
1+
b1100 !
b1100 &
b1100 '
1*
1#
#40000
0%
0#
#45000
0)
1-
0(
b110 !
b110 &
b110 '
1,
1#
#50000
1%
0#
#55000
0+
1)
1.
0*
b1011 !
b1011 &
b1011 '
1(
1#
#60000
0#
0"
#65000
0)
0-
0(
0,
b0 !
b0 &
b0 '
0.
1#
#70000
0#
#75000
1#
#80000
1)
b1000 !
b1000 &
b1000 '
1(
0#
1"
#85000
1+
b1100 !
b1100 &
b1100 '
1*
1#
#90000
0#
#95000
1-
b1110 !
b1110 &
b1110 '
1,
1#
#100000
0%
0#
0$
#105000
1#
#110000
1%
0#
1$
#115000
b1111 !
b1111 &
b1111 '
1.
1#
