digital_circuits/sequential_circuits/flip_flops/T/rtl/T.v
module T (
    input clk,
    input en,
    input areset_n,
    input t,
    output reg q
);
    always @(posedge clk) begin
        if(!areset_n) begin
            q <= 1'b0;
        end
        else if(!en) begin
            q <= q;
        end
        else begin
            if(t) begin
                q <= ~q;
            end
            else begin
                q <= q;
            end
        end

    end
endmodule

digital_circuits/sequential_circuits/flip_flops/T/tb/tb_T.v
`timescale 1ns/1ps

module tb_T;

    reg clk;
    reg en;
    reg areset_n;
    reg t;
    wire q;

    T dut(
        .clk(clk),
        .en(en),
        .areset_n(areset_n),
        .t(t),
        .q(q)
    );

    initial begin
        $dumpfile("waves/dump.vcd");
        $dumpvars(0,tb_T);
    end

    task check;
        reg [2:0] i,j,k;
        begin
            for(i=0;i<2;i=i+1) begin
                for(j=0;j<2;j=j+1) begin
                    for(k=0;k<2;k=k+1) begin
                        @(negedge clk) en=i;
                        @(negedge clk) areset_n=j;
                        @(negedge clk) t=k;
                        #1;
                        $display("en= %b |areset_n= %b |t= %b |q= %b ",en,areset_n,t,q);

                    end
                end
            end
        end
    endtask

    initial begin
        clk = 1'b0;
        forever #5 clk =~clk;
    end

    initial begin 
                
        check();
        
        #10;
        $finish();
    end




endmodule

digital_circuits/sequential_circuits/flip_flops/T/waves/dump.vcd
$date
	Mon Sep 14 11:15:39 2026
$end
$version
	Icarus Verilog
$end
$timescale
	1ps
$end
$scope module tb_T $end
$var wire 1 ! q $end
$var reg 1 " areset_n $end
$var reg 1 # clk $end
$var reg 1 $ en $end
$var reg 1 % t $end
$scope module dut $end
$var wire 1 " areset_n $end
$var wire 1 # clk $end
$var wire 1 $ en $end
$var wire 1 % t $end
$var reg 1 ! q $end
$upscope $end
$scope task check $end
$var reg 3 & i [2:0] $end
$var reg 3 ' j [2:0] $end
$var reg 3 ( k [2:0] $end
$upscope $end
$upscope $end
$enddefinitions $end
$comment Show the parameter values. $end
$dumpall
$end
#0
$dumpvars
b0 (
b0 '
b0 &
x%
x$
0#
x"
x!
$end
#5000
1#
#10000
0$
0#
#15000
1#
#20000
0"
0#
#25000
0!
1#
#30000
0%
0#
#31000
b1 (
#35000
1#
#40000
0#
#45000
1#
#50000
0#
#55000
1#
#60000
1%
0#
#61000
b1 '
b0 (
#65000
1#
#70000
0#
#75000
1#
#80000
1"
0#
#85000
1#
#90000
0%
0#
#91000
b1 (
#95000
1#
#100000
0#
#105000
1#
#110000
0#
#115000
1#
#120000
1%
0#
#121000
b1 &
b0 '
b0 (
#125000
1#
#130000
1$
0#
#135000
1!
1#
#140000
0"
0#
#145000
0!
1#
#150000
0%
0#
#151000
b1 (
#155000
1#
#160000
0#
#165000
1#
#170000
0#
#175000
1#
#180000
1%
0#
#181000
b1 '
b0 (
#185000
1#
#190000
0#
#195000
1#
#200000
1"
0#
#205000
1!
1#
#210000
0%
0#
#211000
b1 (
#215000
1#
#220000
0#
#225000
1#
#230000
0#
#235000
1#
#240000
1%
0#
#241000
b10 &
b10 '
b10 (
#245000
0!
1#
