digital_circuits/sequential_circuits/counter/synchronous_counters/up_counter/mod_8/rtl/D.v
module D (
    input clk,
    input en,
    input areset_n,
    input d,
    output reg q
);

    always @(posedge clk, negedge areset_n) begin
        if(!areset_n) begin
            q <= 1'b0;
        end
        else if(en) begin
            q <= d;
        end
        else begin
            q <= q;
        end
    end

endmodule

digital_circuits/sequential_circuits/counter/asynchronous_counters/down_counter/down_posedge/rtl/down_posedge.v
module down_posedge (
    input clk,
    input en,
    input areset_n,
    output reg [2:0] out
);

    wire [2:0] w;
    D u2(
        .clk(clk),
        .en(en),
        .areset_n(areset_n),
        .d(~w[2]),
        .q(w[2])        
    );

    D u1(
        .clk(w[2]),
        .en(en),
        .areset_n(areset_n),
        .d(~w[1]),
        .q(w[1])        
    );

    D u0(
        .clk(w[1]),
        .en(en),
        .areset_n(areset_n),
        .d(~w[0]),
        .q(w[0])        
    );

    assign {out[2],out[1],out[0]} = {w[0],w[1],w[2]};
    
endmodule

digital_circuits/sequential_circuits/counter/asynchronous_counters/down_counter/down_posedge/tb/tb_down_posedge.v
`timescale 1ns/1ps

module tb_down_posedge;
    reg clk;
    reg en;
    reg areset_n;
    wire [2:0] out;

    down_posedge dut(
        .clk(clk),
        .en(en),
        .areset_n(areset_n),
        .out(out)
    );

    initial begin
        $dumpfile("waves/dump.vcd");
        $dumpvars(0,tb_down_posedge);
    end

    initial begin
        clk = 0;
        forever #5 clk = ~clk;
    end

    initial begin
        en = 0;
        areset_n = 0;
    end

    task check;
        begin
            $display("en = %b | areset_n = %b | out = %b",en,areset_n,out);
        end
    endtask

    initial begin
        #10 areset_n = 1;
        #7 en = 1;

        repeat(20) begin
            @(negedge clk) check();
        end

        #10 $finish; 
    end
endmodule

digital_circuits/sequential_circuits/counter/asynchronous_counters/down_counter/down_posedge/waves/dump.vcd
$date
	Tue Sep 15 08:09:35 2026
$end
$version
	Icarus Verilog
$end
$timescale
	1ps
$end
$scope module tb_down_posedge $end
$var wire 3 ! out [2:0] $end
$var reg 1 " areset_n $end
$var reg 1 # clk $end
$var reg 1 $ en $end
$scope module dut $end
$var wire 1 " areset_n $end
$var wire 1 # clk $end
$var wire 1 $ en $end
$var wire 3 % w [2:0] $end
$var wire 3 & out [2:0] $end
$scope module u0 $end
$var wire 1 " areset_n $end
$var wire 1 ' clk $end
$var wire 1 ( d $end
$var wire 1 $ en $end
$var reg 1 ) q $end
$upscope $end
$scope module u1 $end
$var wire 1 " areset_n $end
$var wire 1 * clk $end
$var wire 1 + d $end
$var wire 1 $ en $end
$var reg 1 , q $end
$upscope $end
$scope module u2 $end
$var wire 1 " areset_n $end
$var wire 1 # clk $end
$var wire 1 - d $end
$var wire 1 $ en $end
$var reg 1 . q $end
$upscope $end
$upscope $end
$scope task check $end
$upscope $end
$upscope $end
$enddefinitions $end
$comment Show the parameter values. $end
$dumpall
$end
#0
$dumpvars
0.
1-
0,
1+
0*
0)
1(
0'
b0 &
b0 %
0$
0#
0"
b0 !
$end
#5000
1#
#10000
0#
1"
#15000
1#
#17000
1$
#20000
0#
#25000
0(
1)
0+
1'
1,
b111 !
b111 &
0-
1*
b111 %
1.
1#
#30000
0#
#35000
b110 !
b110 &
1-
0*
b11 %
0.
1#
#40000
0#
#45000
1+
0'
0,
b101 !
b101 &
0-
1*
b101 %
1.
1#
#50000
0#
#55000
b100 !
b100 &
1-
0*
b1 %
0.
1#
#60000
0#
#65000
1(
0)
0+
1'
1,
b11 !
b11 &
0-
1*
b110 %
1.
1#
#70000
0#
#75000
b10 !
b10 &
1-
0*
b10 %
0.
1#
#80000
0#
#85000
1+
0'
0,
b1 !
b1 &
0-
1*
b100 %
1.
1#
#90000
0#
#95000
b0 !
b0 &
1-
0*
b0 %
0.
1#
#100000
0#
#105000
0(
1)
0+
1'
1,
b111 !
b111 &
0-
1*
b111 %
1.
1#
#110000
0#
#115000
b110 !
b110 &
1-
0*
b11 %
0.
1#
#120000
0#
#125000
1+
0'
0,
b101 !
b101 &
0-
1*
b101 %
1.
1#
#130000
0#
#135000
b100 !
b100 &
1-
0*
b1 %
0.
1#
#140000
0#
#145000
1(
0)
0+
1'
1,
b11 !
b11 &
0-
1*
b110 %
1.
1#
#150000
0#
#155000
b10 !
b10 &
1-
0*
b10 %
0.
1#
#160000
0#
#165000
1+
0'
0,
b1 !
b1 &
0-
1*
b100 %
1.
1#
#170000
0#
#175000
b0 !
b0 &
1-
0*
b0 %
0.
1#
#180000
0#
#185000
0(
1)
0+
1'
1,
b111 !
b111 &
0-
1*
b111 %
1.
1#
#190000
0#
#195000
b110 !
b110 &
1-
0*
b11 %
0.
1#
#200000
0#
#205000
1+
0'
0,
b101 !
b101 &
0-
1*
b101 %
1.
1#
#210000
0#
#215000
b100 !
b100 &
1-
0*
b1 %
0.
1#
