digital_circuits/sequential_circuits/counter/asynchronous_counters/down_counter/mod_10/rtl/mux_D.v
module mux_D(
    input clk,
    input en,
    input areset_n,
    input p_in,
    input qb_in,
    input load,
    output reg out
);

    wire in;

    assign in = (load)?p_in:qb_in;

    always @(posedge clk, negedge areset_n, posedge load) begin
        if(~areset_n) begin
            out <= 0;
        end
        else if(load) begin
            out <= in;
        end
        else if(~en) begin
            out <=out;
        end
        else begin
            out <=in;
        end
    end 

endmodule

digital_circuits/sequential_circuits/counter/asynchronous_counters/down_counter/mod_10/rtl/mod_10.v
module mod_10(
    input clk,
    input en,
    input areset_n,
    output [3:0] out
);

    wire [3:0] w;
    wire load;
    wire [3:0] p_in;
    assign p_in = 4'b1001;

    mux_D u3(
        .clk(clk),
        .en(en),
        .areset_n(areset_n),
        .p_in(p_in[3]),
        .qb_in(~w[3]),
        .load(load),
        .out(w[3])
    );

    mux_D u2(
        .clk(w[3]),
        .en(en),
        .areset_n(areset_n),
        .p_in(p_in[2]),
        .qb_in(~w[2]),
        .load(load),
        .out(w[2])
    );

    mux_D u1(
        .clk(w[2]),
        .en(en),
        .areset_n(areset_n),
        .p_in(p_in[1]),
        .qb_in(~w[1]),
        .load(load),
        .out(w[1])
    );

    mux_D u0(
        .clk(w[1]),
        .en(en),
        .areset_n(areset_n),
        .p_in(p_in[0]),
        .qb_in(~w[0]),
        .load(load),
        .out(w[0])
    );

    assign load = w[3] & w[2] & w[1] & w[0];
    
    assign {out[3],out[2],out[1],out[0]}= {w[0],w[1],w[2],w[3]};


endmodule

digital_circuits/sequential_circuits/counter/asynchronous_counters/down_counter/mod_10/tb/tb_mod_10.v
`timescale 1ns/1ps

module tb_mod_10;
    reg clk;
    reg en;
    reg areset_n;
    wire [3:0] out;

    mod_10 dut(
        .clk(clk),
        .en(en),
        .areset_n(areset_n),
        .out(out)
    );

    initial begin
        $dumpfile("waves/dump.vcd");
        $dumpvars(0,tb_mod_10);
    end

    initial begin
        clk = 0;
        forever #5 clk = ~clk;
    end

    initial begin
        en = 0;
        areset_n = 0;
    end

    task check;
        begin
            $display("en = %b | areset_n = %b | out = %b",en,areset_n,out);
        end
    endtask

    initial begin
        #25 areset_n = 1;
        #7 en = 1; 

        repeat(30) begin
            @(negedge clk) check();
        end

        #10 $finish; 
    end
endmodule

digital_circuits/sequential_circuits/counter/asynchronous_counters/down_counter/mod_10/waves/dump.vcd
$date
	Wed Sep 16 08:11:25 2026
$end
$version
	Icarus Verilog
$end
$timescale
	1ps
$end
$scope module tb_mod_10 $end
$var wire 4 ! out [3:0] $end
$var reg 1 " areset_n $end
$var reg 1 # clk $end
$var reg 1 $ en $end
$scope module dut $end
$var wire 1 " areset_n $end
$var wire 1 # clk $end
$var wire 1 $ en $end
$var wire 1 % load $end
$var wire 4 & p_in [3:0] $end
$var wire 4 ' w [3:0] $end
$var wire 4 ( out [3:0] $end
$scope module u0 $end
$var wire 1 " areset_n $end
$var wire 1 ) clk $end
$var wire 1 $ en $end
$var wire 1 % load $end
$var wire 1 * p_in $end
$var wire 1 + qb_in $end
$var wire 1 , in $end
$var reg 1 - out $end
$upscope $end
$scope module u1 $end
$var wire 1 " areset_n $end
$var wire 1 . clk $end
$var wire 1 $ en $end
$var wire 1 % load $end
$var wire 1 / p_in $end
$var wire 1 0 qb_in $end
$var wire 1 1 in $end
$var reg 1 2 out $end
$upscope $end
$scope module u2 $end
$var wire 1 " areset_n $end
$var wire 1 3 clk $end
$var wire 1 $ en $end
$var wire 1 % load $end
$var wire 1 4 p_in $end
$var wire 1 5 qb_in $end
$var wire 1 6 in $end
$var reg 1 7 out $end
$upscope $end
$scope module u3 $end
$var wire 1 " areset_n $end
$var wire 1 # clk $end
$var wire 1 $ en $end
$var wire 1 % load $end
$var wire 1 8 p_in $end
$var wire 1 9 qb_in $end
$var wire 1 : in $end
$var reg 1 ; out $end
$upscope $end
$upscope $end
$scope task check $end
$upscope $end
$upscope $end
$enddefinitions $end
$comment Show the parameter values. $end
$dumpall
$end
#0
$dumpvars
0;
1:
19
18
07
16
15
04
03
02
11
10
0/
0.
0-
1,
1+
1*
0)
b0 (
b0 '
b1001 &
0%
0$
0#
0"
b0 !
$end
#5000
1#
#10000
0#
#15000
1#
#20000
0#
#25000
1#
1"
#30000
0#
#32000
1$
#35000
0,
0%
0+
1-
11
10
0)
02
16
15
0.
07
0:
b1001 !
b1001 (
09
13
b1001 '
1;
1#
#40000
0#
#45000
1:
b1000 !
b1000 (
19
03
b1 '
0;
1#
#50000
0#
#55000
1-
0,
0%
11
10
0)
02
16
15
0.
07
0:
b1001 !
b1001 (
09
13
b1001 '
1;
1#
#60000
0#
#65000
1:
b1000 !
b1000 (
19
03
b1 '
0;
1#
#70000
0#
#75000
1-
0,
0%
11
10
0)
02
16
15
0.
07
0:
b1001 !
b1001 (
09
13
b1001 '
1;
1#
#80000
0#
#85000
1:
b1000 !
b1000 (
19
03
b1 '
0;
1#
#90000
0#
#95000
1-
0,
0%
11
10
0)
02
16
15
0.
07
0:
b1001 !
b1001 (
09
13
b1001 '
1;
1#
#100000
0#
#105000
1:
b1000 !
b1000 (
19
03
b1 '
0;
1#
#110000
0#
#115000
1-
0,
0%
11
10
0)
02
16
15
0.
07
0:
b1001 !
b1001 (
09
13
b1001 '
1;
1#
#120000
0#
#125000
1:
b1000 !
b1000 (
19
03
b1 '
0;
1#
#130000
0#
#135000
1-
0,
0%
11
10
0)
02
16
15
0.
07
0:
b1001 !
b1001 (
09
13
b1001 '
1;
1#
#140000
0#
#145000
1:
b1000 !
b1000 (
19
03
b1 '
0;
1#
#150000
0#
#155000
1-
0,
0%
11
10
0)
02
16
15
0.
07
0:
b1001 !
b1001 (
09
13
b1001 '
1;
1#
#160000
0#
#165000
1:
b1000 !
b1000 (
19
03
b1 '
0;
1#
#170000
0#
#175000
1-
0,
0%
11
10
0)
02
16
15
0.
07
0:
b1001 !
b1001 (
09
13
b1001 '
1;
1#
#180000
0#
#185000
1:
b1000 !
b1000 (
19
03
b1 '
0;
1#
#190000
0#
#195000
1-
0,
0%
11
10
0)
02
16
15
0.
07
0:
b1001 !
b1001 (
09
13
b1001 '
1;
1#
#200000
0#
#205000
1:
b1000 !
b1000 (
19
03
b1 '
0;
1#
#210000
0#
#215000
1-
0,
0%
11
10
0)
02
16
15
0.
07
0:
b1001 !
b1001 (
09
13
b1001 '
1;
1#
#220000
0#
#225000
1:
b1000 !
b1000 (
19
03
b1 '
0;
1#
#230000
0#
#235000
1-
0,
0%
11
10
0)
02
16
15
0.
07
0:
b1001 !
b1001 (
09
13
b1001 '
1;
1#
#240000
0#
#245000
1:
b1000 !
b1000 (
19
03
b1 '
0;
1#
#250000
0#
#255000
1-
0,
0%
11
10
0)
02
16
15
0.
07
0:
b1001 !
b1001 (
09
13
b1001 '
1;
1#
#260000
0#
#265000
1:
b1000 !
b1000 (
19
03
b1 '
0;
1#
#270000
0#
#275000
1-
0,
0%
11
10
0)
02
16
15
0.
07
0:
b1001 !
b1001 (
09
13
b1001 '
1;
1#
#280000
0#
#285000
1:
b1000 !
b1000 (
19
03
b1 '
0;
1#
#290000
0#
#295000
1-
0,
0%
11
10
0)
02
16
15
0.
07
0:
b1001 !
b1001 (
09
13
b1001 '
1;
1#
#300000
0#
#305000
1:
b1000 !
b1000 (
19
03
b1 '
0;
1#
#310000
0#
#315000
1-
0,
0%
11
10
0)
02
16
15
0.
07
0:
b1001 !
b1001 (
09
13
b1001 '
1;
1#
#320000
0#
#325000
1:
b1000 !
b1000 (
19
03
b1 '
0;
1#
#330000
0#
#335000
1-
0,
0%
11
10
0)
02
16
15
0.
07
0:
b1001 !
b1001 (
09
13
b1001 '
1;
1#
