digital_circuits/combinational_circuit/mux_2to1/rtl/mux_2to1_procedural.v
module mux_2to1_procedural(
    input a,
    input b,
    input sel,
    output reg out
);
    always @(a or b or sel) begin
        out=sel?b:a;
    end
endmodule

week2/combinational_circuit/mux_2to1/tb/tb_mux_2to1_procedural.v
`timescale 1ns/1ps
module tb_mux_2to1_procedural;
    reg a;
    reg b;
    reg sel;
    wire out;
    mux_2to1_procedural dut(
        .a(a),
        .b(b),
        .sel(sel),
        .out(out)
    );
    initial begin
        $dumpfile("waves/dump.vcd");
        $dumpvars(0,tb_mux_2to1_procedural);
    end
    
    integer passed=0;
    integer failed=0;
    

    task check;
        input t_a, t_b, t_sel;
        input exp_out;
        begin
            a = t_a;
            b = t_b;
            sel =t_sel;
            #10;
            if(out === exp_out) begin
                $display("PASS: a=%b b=%b sel=%b out=%b", a,b,sel,out);
                passed=passed+1;
            end
            else begin
                $display("FAILED: a=%b b=%b sel=%b out=%b | exp_out=5%b", a,b,sel,out,exp_out);
                failed=failed+1;
            end
        end
    endtask
    initial begin
        integer i;
        for(i=0;i<8;i=i+1) begin
            check(i[2],i[1],i[0],((i[0])?i[1]:i[2]));
        end
        $display("Test summary: %d passed, %d failed", passed, failed);
        $finish;
    end
endmodule

week2/combinational_circuit/mux_2to1/waves/dump.vcd
$date
	Thu May 28 14:13:33 2026
$end
$version
	Icarus Verilog
$end
$timescale
	1ps
$end
$scope module tb_mux_2to1_procedural $end
$var wire 1 ! out $end
$var reg 1 " a $end
$var reg 1 # b $end
$var reg 1 $ sel $end
$var integer 32 % failed [31:0] $end
$var integer 32 & passed [31:0] $end
$scope module dut $end
$var wire 1 " a $end
$var wire 1 # b $end
$var wire 1 $ sel $end
$var reg 1 ! out $end
$upscope $end
$scope begin $unm_blk_6 $end
$var integer 32 ' i [31:0] $end
$upscope $end
$scope task check $end
$var reg 1 ( exp_out $end
$var reg 1 ) t_a $end
$var reg 1 * t_b $end
$var reg 1 + t_sel $end
$upscope $end
$upscope $end
$enddefinitions $end
$comment Show the parameter values. $end
$dumpall
$end
#0
$dumpvars
0+
0*
0)
0(
b0 '
b0 &
b0 %
0$
0#
0"
0!
$end
#10000
1$
1+
b1 '
b1 &
#20000
0$
1#
0+
1*
b10 '
b10 &
#30000
1!
1$
1(
1+
b11 '
b11 &
#40000
0$
0#
1"
0+
0*
1)
b100 '
b100 &
#50000
0!
1$
0(
1+
b101 '
b101 &
#60000
1!
0$
1#
1(
0+
1*
b110 '
b110 &
#70000
1$
1+
b111 '
b111 &
#80000
b1000 '
b1000 &
