week2/combinational_circuit/alu_4bit/rtl/alu_4bit.v
module alu_4bit (
    input signed [3:0] a, b,
    input [2:0] opcode,
    output zero,
    output negative,
    output reg overflow,
    output reg carry_out,
    output reg [3:0] out
);

    assign zero = (out == 4'b0000);
    assign negative = (out[3] == 1'b1);
    

    always @(*) begin
        out = 4'b0000;
        carry_out = 1'b0;
        overflow = 1'b0;
        
        case (opcode)
            3'b000: begin
                {carry_out,out} = {1'b0,a} + {1'b0,b};
                overflow = (a[3] == b[3]) && (a[3] != out[3]);
            end
            
            3'b001: begin
                {carry_out,out} = {1'b0,a} - {1'b0,b};
                overflow = (a[3] != b[3]) && (a[3] != out[3]);
            end
            3'b010: out = a&b;
            3'b011: out = a | b;
            3'b100: out = a ^ b;
            3'b101: out = ~a;
            3'b110: begin
                // a - 1 1 1 1 -> 1 1 1 0
                out = a << 1;
                carry_out = a[3];
            end 
            3'b111: begin
                // a - 1 1 1 1 -> 0 1 1 1
                out = a >>> 1;
                carry_out = a[0];
            end
            default: begin
                out= 4'bxxxx;
                carry_out = 1'bx;
                overflow= 1'bx;
            end
        endcase
    end


endmodule

week2/combinational_circuit/alu_4bit/tb/tb_alu_4bit.v
`timescale 1ns/1ps
module tb_alu_4bit;

    reg signed [3:0] a, b;
    reg [2:0] opcode;
    wire zero;
    wire negative;
    wire overflow;
    wire carry_out;
    wire [3:0] out;

    alu_4bit dut (
        .a(a),
        .b(b),
        .opcode(opcode),
        .zero(zero),
        .negative(negative),
        .overflow(overflow),
        .carry_out(carry_out),
        .out(out)
    );

    initial begin
        $dumpfile("waves/dump.vcd");
        $dumpvars(0,tb_alu_4bit);
    end

    integer pass=0;
    integer fail=0;

    task exhaustive;
        reg exp_zero;
        reg exp_negative;
        reg exp_overflow;
        reg exp_carry_out;
        reg [3:0] exp_out;
        reg [4:0] i, j;
        
        reg [3:0] o;
        begin
            for(i=0;i<16;i=i+1) begin
                a=i[3:0];
                for (j=0;j<16;j=j+1) begin
                    b=j[3:0];
                    for(o=0;o<8;o=o+1) begin
                        opcode = o;
                        exp_out=0;
                        exp_carry_out=0;
                        exp_overflow=0;
                        case (opcode) 
                            3'b000: begin
                                {exp_carry_out,exp_out} = {1'b0,a} + {1'b0,b};
                                exp_overflow = (a[3] == b[3]) && (a[3] != exp_out[3]);
                             end
            
                            3'b001: begin
                                {exp_carry_out,exp_out} = {1'b0,a} - {1'b0,b};
                                exp_overflow = (a[3] != b[3]) && (a[3] != exp_out[3]);
                            end
                            3'b010: exp_out = a&b;
                            3'b011: exp_out = a | b;
                            3'b100: exp_out = a ^ b;
                            3'b101: exp_out = ~a;
                            3'b110: begin
                                // a - 1 1 1 1 -> 1 1 1 0
                                exp_out = a << 1;
                                exp_carry_out = a[3];
                            end 
                            3'b111: begin
                                // a - 1 1 1 1 -> 0 1 1 1
                                exp_out = a >>> 1;
                                exp_carry_out = a[0];
                            end
                            default: begin
                                exp_out= 4'bxxxx;
                                exp_carry_out = 1'bx;
                                exp_overflow = 1'bx;
                            end
                        endcase
                        exp_zero = (exp_out == 4'b0000);
                        exp_negative = (exp_out[3] == 1'b1);
                        #10;
                        if(exp_zero === zero && exp_negative === negative && exp_overflow === overflow && exp_carry_out === carry_out && exp_out === out) begin
                            $display("PASS: a=%d a=%b b=%d b=%b opcode=%b | zero=%b negative=%b overflow=%b carry_out=%b out=%b",a,a,b,b,opcode,zero,negative,overflow,carry_out,out);
                            pass=pass+1;
                        end
                        else begin
                            $display("FAIL: a=%d a=%b b=%d b=%b opcode=%b | zero=%b negative=%b overflow=%b carry_out=%b out=%b | exp_zero=%b exp_negative=%b exp_overflow=%b exp_carry_out=%b exp_out=%b",a,a,b,b,opcode,zero,negative,overflow,carry_out,out,exp_zero,exp_negative,exp_overflow,exp_carry_out,exp_out);
                            fail=fail+1;
                        end

                    end
                end

            end
            
        end
    endtask

    task opcode_sweep;
        input signed [3:0] t_a, t_b;
        reg exp_zero;
        reg exp_negative;
        reg exp_overflow;
        reg exp_carry_out;
        reg [3:0] exp_out;
        reg [3:0] o;
        begin
            a=t_a; b=t_b;
            for(o=0;o<8;o=o+1) begin
                opcode=o;
                exp_zero=0;
                exp_negative=0;
                exp_overflow=0;
                exp_carry_out=0;
                exp_out=0;
                case (opcode) 
                3'b000: begin
                    {exp_carry_out,exp_out} = {1'b0,a} + {1'b0,b};
                    exp_overflow = (a[3] == b[3]) && (a[3] != exp_out[3]);
                 end
            
                3'b001: begin
                    {exp_carry_out,exp_out} = {1'b0,a} - {1'b0,b};
                    exp_overflow = (a[3] != b[3]) && (a[3] != exp_out[3]);
                end
                3'b010: exp_out = a&b;
                3'b011: exp_out = a | b;
                3'b100: exp_out = a ^ b;
                3'b101: exp_out = ~a;
                3'b110: begin
                    // a - 1 1 1 1 -> 1 1 1 0
                    exp_out = a << 1;
                    exp_carry_out = a[3];
                end 
                3'b111: begin
                    // a - 1 1 1 1 -> 0 1 1 1
                    exp_out = a >>> 1;
                    exp_carry_out = a[0];
                end
                default: begin
                    exp_out= 4'bxxxx;
                    exp_carry_out = 1'bx;
                    exp_overflow = 1'bx;
                end
                endcase
                exp_zero = (exp_out == 4'b0000);
                exp_negative = (exp_out[3] == 1'b1);
                #10;
                if(exp_zero === zero && exp_negative === negative && exp_overflow === overflow && exp_carry_out === carry_out && exp_out === out) begin
                    $display("PASS: a=%d a=%b b=%d b=%b opcode=%b | zero=%b negative=%b overflow=%b carry_out=%b out=%b",a,a,b,b,opcode,zero,negative,overflow,carry_out,out);
                    pass=pass+1;
                end
                else begin
                    $display("FAIL: a=%d a=%b b=%d b=%b opcode=%b | zero=%b negative=%b overflow=%b carry_out=%b out=%b | exp_zero=%b exp_negative=%b exp_overflow=%b exp_carry_out=%b exp_out=%b",a,a,b,b,opcode,zero,negative,overflow,carry_out,out,exp_zero,exp_negative,exp_overflow,exp_carry_out,exp_out);
                    fail=fail+1;
                end

                
            end
        end

    endtask

    task input_sweep;
        input [3:0] t_opcode;
        reg exp_zero;
        reg exp_negative;
        reg exp_overflow;
        reg exp_carry_out;
        reg [3:0] exp_out;
        reg [4:0] i, j;
        
        
        begin
            for(i=0;i<16;i=i+1) begin
                a=i[3:0];
                for (j=0;j<16;j=j+1) begin
                    b=j[3:0];
                    
                        opcode = t_opcode;
                        exp_out=0;
                        exp_carry_out=0;
                        exp_overflow=0;
                        case (opcode) 
                            3'b000: begin
                                {exp_carry_out,exp_out} = {1'b0,a} + {1'b0,b};
                                exp_overflow = (a[3] == b[3]) && (a[3] != exp_out[3]);
                             end
            
                            3'b001: begin
                                {exp_carry_out,exp_out} = {1'b0,a} - {1'b0,b};
                                exp_overflow = (a[3] != b[3]) && (a[3] != exp_out[3]);
                            end
                            3'b010: exp_out = a&b;
                            3'b011: exp_out = a | b;
                            3'b100: exp_out = a ^ b;
                            3'b101: exp_out = ~a;
                            3'b110: begin
                                // a - 1 1 1 1 -> 1 1 1 0
                                exp_out = a << 1;
                                exp_carry_out = a[3];
                            end 
                            3'b111: begin
                                // a - 1 1 1 1 -> 0 1 1 1
                                exp_out = a >>> 1;
                                exp_carry_out = a[0];
                            end
                            default: begin
                                exp_out= 4'bxxxx;
                                exp_carry_out = 1'bx;
                                exp_overflow = 1'bx;
                            end
                        endcase
                        exp_zero = (exp_out == 4'b0000);
                        exp_negative = (exp_out[3] == 1'b1);
                        #10;
                        if(exp_zero === zero && exp_negative === negative && exp_overflow === overflow && exp_carry_out === carry_out && exp_out === out) begin
                            $display("PASS: a=%d a=%b b=%d b=%b opcode=%b | zero=%b negative=%b overflow=%b carry_out=%b out=%b",a,a,b,b,opcode,zero,negative,overflow,carry_out,out);
                            pass=pass+1;
                        end
                        else begin
                            $display("FAIL: a=%d a=%b b=%d b=%b opcode=%b | zero=%b negative=%b overflow=%b carry_out=%b out=%b | exp_zero=%b exp_negative=%b exp_overflow=%b exp_carry_out=%b exp_out=%b",a,a,b,b,opcode,zero,negative,overflow,carry_out,out,exp_zero,exp_negative,exp_overflow,exp_carry_out,exp_out);
                            fail=fail+1;
                        end

                    
                end

            end
            
        end
    endtask

    task check;
        input signed [3:0] t_a, t_b;
        input [3:0] t_opcode;
        reg exp_zero;
        reg exp_negative;
        reg exp_overflow;
        reg exp_carry_out;
        reg [3:0] exp_out;
        
        begin
            a=t_a; b=t_b;
            
                opcode=t_opcode;
                exp_zero=0;
                exp_negative=0;
                exp_overflow=0;
                exp_carry_out=0;
                exp_out=0;
                case (opcode) 
                3'b000: begin
                    {exp_carry_out,exp_out} = {1'b0,a} + {1'b0,b};
                    exp_overflow = (a[3] == b[3]) && (a[3] != exp_out[3]);
                 end
            
                3'b001: begin
                    {exp_carry_out,exp_out} = {1'b0,a} - {1'b0,b};
                    exp_overflow = (a[3] != b[3]) && (a[3] != exp_out[3]);
                end
                3'b010: exp_out = a&b;
                3'b011: exp_out = a | b;
                3'b100: exp_out = a ^ b;
                3'b101: exp_out = ~a;
                3'b110: begin
                    // a - 1 1 1 1 -> 1 1 1 0
                    exp_out = a << 1;
                    exp_carry_out = a[3];
                end 
                3'b111: begin
                    // a - 1 1 1 1 -> 0 1 1 1
                    exp_out = a >>> 1;
                    exp_carry_out = a[0];
                end
                default: begin
                    exp_out= 4'bxxxx;
                    exp_carry_out = 1'bx;
                    exp_overflow = 1'bx;
                end
                endcase
                exp_zero = (exp_out == 4'b0000);
                exp_negative = (exp_out[3] == 1'b1);
                #10;
                if(exp_zero === zero && exp_negative === negative && exp_overflow === overflow && exp_carry_out === carry_out && exp_out === out) begin
                    $display("PASS: a=%d a=%b b=%d b=%b opcode=%b | zero=%b negative=%b overflow=%b carry_out=%b out=%b",a,a,b,b,opcode,zero,negative,overflow,carry_out,out);
                    pass=pass+1;
                end
                else begin
                    $display("FAIL: a=%d a=%b b=%d b=%b opcode=%b | zero=%b negative=%b overflow=%b carry_out=%b out=%b | exp_zero=%b exp_negative=%b exp_overflow=%b exp_carry_out=%b exp_out=%b",a,a,b,b,opcode,zero,negative,overflow,carry_out,out,exp_zero,exp_negative,exp_overflow,exp_carry_out,exp_out);
                    fail=fail+1;
                end

                
            
        end

    endtask

    initial begin
        exhaustive();
        opcode_sweep(-4,5);
        input_sweep(3'b000);
        check(0,0,3'b000);
        check(4'b1111,4'b1111,3'b000);
        check(-8,-8,3'b000);
        check(7,7,3'b000);
        check(1,0,3'b001);
        check(0,1,3'b001);


        $display("Test summary:");
        $display("PASS:%d",pass);
        $display("FAIL:%d",fail);
        $finish;
    end

endmodule

digital_circuits/combinational_circuit/alu_4bit/waves/dump.vcd
$date
	Thu Jun  4 16:22:58 2026
$end
$version
	Icarus Verilog
$end
$timescale
	1ps
$end
$scope module tb_alu_4bit $end
$var wire 1 ! zero $end
$var wire 1 " overflow $end
$var wire 4 # out [3:0] $end
$var wire 1 $ negative $end
$var wire 1 % carry_out $end
$var reg 4 & a [3:0] $end
$var reg 4 ' b [3:0] $end
$var reg 3 ( opcode [2:0] $end
$var integer 32 ) fail [31:0] $end
$var integer 32 * pass [31:0] $end
$scope module dut $end
$var wire 4 + a [3:0] $end
$var wire 4 , b [3:0] $end
$var wire 1 $ negative $end
$var wire 3 - opcode [2:0] $end
$var wire 1 ! zero $end
$var reg 1 % carry_out $end
$var reg 4 . out [3:0] $end
$var reg 1 " overflow $end
$upscope $end
$scope task check $end
$var reg 1 / exp_carry_out $end
$var reg 1 0 exp_negative $end
$var reg 4 1 exp_out [3:0] $end
$var reg 1 2 exp_overflow $end
$var reg 1 3 exp_zero $end
$var reg 4 4 t_a [3:0] $end
$var reg 4 5 t_b [3:0] $end
$var reg 4 6 t_opcode [3:0] $end
$upscope $end
$scope task exhaustive $end
$var reg 1 7 exp_carry_out $end
$var reg 1 8 exp_negative $end
$var reg 4 9 exp_out [3:0] $end
$var reg 1 : exp_overflow $end
$var reg 1 ; exp_zero $end
$var reg 5 < i [4:0] $end
$var reg 5 = j [4:0] $end
$var reg 4 > o [3:0] $end
$upscope $end
$scope task input_sweep $end
$var reg 1 ? exp_carry_out $end
$var reg 1 @ exp_negative $end
$var reg 4 A exp_out [3:0] $end
$var reg 1 B exp_overflow $end
$var reg 1 C exp_zero $end
$var reg 5 D i [4:0] $end
$var reg 5 E j [4:0] $end
$var reg 4 F t_opcode [3:0] $end
$upscope $end
$scope task opcode_sweep $end
$var reg 1 G exp_carry_out $end
$var reg 1 H exp_negative $end
$var reg 4 I exp_out [3:0] $end
$var reg 1 J exp_overflow $end
$var reg 1 K exp_zero $end
$var reg 4 L o [3:0] $end
$var reg 4 M t_a [3:0] $end
$var reg 4 N t_b [3:0] $end
$upscope $end
$upscope $end
$enddefinitions $end
$comment Show the parameter values. $end
$dumpall
$end
#0
$dumpvars
bx N
bx M
bx L
xK
xJ
bx I
xH
xG
bx F
bx E
bx D
xC
xB
bx A
x@
x?
b0 >
b0 =
b0 <
1;
0:
b0 9
08
07
bx 6
bx 5
bx 4
x3
x2
bx 1
x0
x/
b0 .
b0 -
b0 ,
b0 +
b0 *
b0 )
b0 (
b0 '
b0 &
0%
0$
b0 #
0"
1!
$end
#10000
b1 (
b1 -
b1 >
b1 *
#20000
b10 (
b10 -
b10 >
b10 *
#30000
b11 (
b11 -
b11 >
b11 *
#40000
b100 (
b100 -
b100 >
b100 *
#50000
1$
0!
b1111 #
b1111 .
18
0;
b1111 9
b101 (
b101 -
b101 >
b101 *
#60000
0$
1!
b0 #
b0 .
08
1;
b0 9
b110 (
b110 -
b110 >
b110 *
#70000
b111 (
b111 -
b111 >
b111 *
#80000
0!
b1 #
b1 .
0;
b1 9
b0 (
b0 -
b1 '
b1 ,
b1 =
b0 >
b1000 *
#90000
1$
1%
0!
b1111 #
b1111 .
18
17
b1111 9
b1 (
b1 -
b1 >
b1001 *
#100000
0$
0%
1!
b0 #
b0 .
08
1;
07
b0 9
b10 (
b10 -
b10 >
b1010 *
#110000
0!
b1 #
b1 .
0;
b1 9
b11 (
b11 -
b11 >
b1011 *
#120000
0!
b1 #
b1 .
b1 9
b100 (
b100 -
b100 >
b1100 *
#130000
1$
0!
b1111 #
b1111 .
18
b1111 9
b101 (
b101 -
b101 >
b1101 *
#140000
0$
1!
b0 #
b0 .
08
1;
b0 9
b110 (
b110 -
b110 >
b1110 *
#150000
b111 (
b111 -
b111 >
b1111 *
#160000
0!
b10 #
b10 .
0;
b10 9
b0 (
b0 -
b10 '
b10 ,
b10 =
b0 >
b10000 *
#170000
1$
1%
0!
b1110 #
b1110 .
18
17
b1110 9
b1 (
b1 -
b1 >
b10001 *
#180000
0$
0%
1!
b0 #
b0 .
08
1;
07
b0 9
b10 (
b10 -
b10 >
b10010 *
#190000
0!
b10 #
b10 .
0;
b10 9
b11 (
b11 -
b11 >
b10011 *
#200000
0!
b10 #
b10 .
b10 9
b100 (
b100 -
b100 >
b10100 *
#210000
1$
0!
b1111 #
b1111 .
18
b1111 9
b101 (
b101 -
b101 >
b10101 *
#220000
0$
1!
b0 #
b0 .
08
1;
b0 9
b110 (
b110 -
b110 >
b10110 *
#230000
b111 (
b111 -
b111 >
b10111 *
#240000
0!
b11 #
b11 .
0;
b11 9
b0 (
b0 -
b11 '
b11 ,
b11 =
b0 >
b11000 *
#250000
1$
1%
0!
b1101 #
b1101 .
18
17
b1101 9
b1 (
b1 -
b1 >
b11001 *
#260000
0$
0%
1!
b0 #
b0 .
08
1;
07
b0 9
b10 (
b10 -
b10 >
b11010 *
#270000
0!
b11 #
b11 .
0;
b11 9
b11 (
b11 -
b11 >
b11011 *
#280000
0!
b11 #
b11 .
b11 9
b100 (
b100 -
b100 >
b11100 *
#290000
1$
0!
b1111 #
b1111 .
18
b1111 9
b101 (
b101 -
b101 >
b11101 *
#300000
0$
1!
b0 #
b0 .
08
1;
b0 9
b110 (
b110 -
b110 >
b11110 *
#310000
b111 (
b111 -
b111 >
b11111 *
#320000
0!
b100 #
b100 .
0;
b100 9
b0 (
b0 -
b100 '
b100 ,
b100 =
b0 >
b100000 *
#330000
1$
1%
0!
b1100 #
b1100 .
18
17
b1100 9
b1 (
b1 -
b1 >
b100001 *
#340000
0$
0%
1!
b0 #
b0 .
08
1;
07
b0 9
b10 (
b10 -
b10 >
b100010 *
#350000
0!
b100 #
b100 .
0;
b100 9
b11 (
b11 -
b11 >
b100011 *
#360000
0!
b100 #
b100 .
b100 9
b100 (
b100 -
b100 >
b100100 *
#370000
1$
0!
b1111 #
b1111 .
18
b1111 9
b101 (
b101 -
b101 >
b100101 *
#380000
0$
1!
b0 #
b0 .
08
1;
b0 9
b110 (
b110 -
b110 >
b100110 *
#390000
b111 (
b111 -
b111 >
b100111 *
#400000
0!
b101 #
b101 .
0;
b101 9
b0 (
b0 -
b101 '
b101 ,
b101 =
b0 >
b101000 *
#410000
1$
1%
0!
b1011 #
b1011 .
18
17
b1011 9
b1 (
b1 -
b1 >
b101001 *
#420000
0$
0%
1!
b0 #
b0 .
08
1;
07
b0 9
b10 (
b10 -
b10 >
b101010 *
#430000
0!
b101 #
b101 .
0;
b101 9
b11 (
b11 -
b11 >
b101011 *
#440000
0!
b101 #
b101 .
b101 9
b100 (
b100 -
b100 >
b101100 *
#450000
1$
0!
b1111 #
b1111 .
18
b1111 9
b101 (
b101 -
b101 >
b101101 *
#460000
0$
1!
b0 #
b0 .
08
1;
b0 9
b110 (
b110 -
b110 >
b101110 *
#470000
b111 (
b111 -
b111 >
b101111 *
#480000
0!
b110 #
b110 .
0;
b110 9
b0 (
b0 -
b110 '
b110 ,
b110 =
b0 >
b110000 *
#490000
1$
1%
0!
b1010 #
b1010 .
18
17
b1010 9
b1 (
b1 -
b1 >
b110001 *
#500000
0$
0%
1!
b0 #
b0 .
08
1;
07
b0 9
b10 (
b10 -
b10 >
b110010 *
#510000
0!
b110 #
b110 .
0;
b110 9
b11 (
b11 -
b11 >
b110011 *
#520000
0!
b110 #
b110 .
b110 9
b100 (
b100 -
b100 >
b110100 *
#530000
1$
0!
b1111 #
b1111 .
18
b1111 9
b101 (
b101 -
b101 >
b110101 *
#540000
0$
1!
b0 #
b0 .
08
1;
b0 9
b110 (
b110 -
b110 >
b110110 *
#550000
b111 (
b111 -
b111 >
b110111 *
#560000
0!
b111 #
b111 .
0;
b111 9
b0 (
b0 -
b111 '
b111 ,
b111 =
b0 >
b111000 *
#570000
1$
1%
0!
b1001 #
b1001 .
18
17
b1001 9
b1 (
b1 -
b1 >
b111001 *
#580000
0$
0%
1!
b0 #
b0 .
08
1;
07
b0 9
b10 (
b10 -
b10 >
b111010 *
#590000
0!
b111 #
b111 .
0;
b111 9
b11 (
b11 -
b11 >
b111011 *
#600000
0!
b111 #
b111 .
b111 9
b100 (
b100 -
b100 >
b111100 *
#610000
1$
0!
b1111 #
b1111 .
18
b1111 9
b101 (
b101 -
b101 >
b111101 *
#620000
0$
1!
b0 #
b0 .
08
1;
b0 9
b110 (
b110 -
b110 >
b111110 *
#630000
b111 (
b111 -
b111 >
b111111 *
#640000
1$
0!
b1000 #
b1000 .
18
0;
b1000 9
b0 (
b0 -
b1000 '
b1000 ,
b1000 =
b0 >
b1000000 *
#650000
1"
1%
0!
b1000 #
b1000 .
1:
17
b1000 9
b1 (
b1 -
b1 >
b1000001 *
#660000
0$
0"
0%
1!
b0 #
b0 .
08
1;
0:
07
b0 9
b10 (
b10 -
b10 >
b1000010 *
#670000
1$
0!
b1000 #
b1000 .
18
0;
b1000 9
b11 (
b11 -
b11 >
b1000011 *
#680000
0!
b1000 #
b1000 .
b1000 9
b100 (
b100 -
b100 >
b1000100 *
#690000
0!
b1111 #
b1111 .
b1111 9
b101 (
b101 -
b101 >
b1000101 *
#700000
0$
1!
b0 #
b0 .
08
1;
b0 9
b110 (
b110 -
b110 >
b1000110 *
#710000
b111 (
b111 -
b111 >
b1000111 *
#720000
1$
0!
b1001 #
b1001 .
18
0;
b1001 9
b0 (
b0 -
b1001 '
b1001 ,
b1001 =
b0 >
b1001000 *
#730000
0$
1%
0!
b111 #
b111 .
08
17
b111 9
b1 (
b1 -
b1 >
b1001001 *
#740000
0%
1!
b0 #
b0 .
1;
07
b0 9
b10 (
b10 -
b10 >
b1001010 *
#750000
1$
0!
b1001 #
b1001 .
18
0;
b1001 9
b11 (
b11 -
b11 >
b1001011 *
#760000
0!
b1001 #
b1001 .
b1001 9
b100 (
b100 -
b100 >
b1001100 *
#770000
0!
b1111 #
b1111 .
b1111 9
b101 (
b101 -
b101 >
b1001101 *
#780000
0$
1!
b0 #
b0 .
08
1;
b0 9
b110 (
b110 -
b110 >
b1001110 *
#790000
b111 (
b111 -
b111 >
b1001111 *
#800000
1$
0!
b1010 #
b1010 .
18
0;
b1010 9
b0 (
b0 -
b1010 '
b1010 ,
b1010 =
b0 >
b1010000 *
#810000
0$
1%
0!
b110 #
b110 .
08
17
b110 9
b1 (
b1 -
b1 >
b1010001 *
#820000
0%
1!
b0 #
b0 .
1;
07
b0 9
b10 (
b10 -
b10 >
b1010010 *
#830000
1$
0!
b1010 #
b1010 .
18
0;
b1010 9
b11 (
b11 -
b11 >
b1010011 *
#840000
0!
b1010 #
b1010 .
b1010 9
b100 (
b100 -
b100 >
b1010100 *
#850000
0!
b1111 #
b1111 .
b1111 9
b101 (
b101 -
b101 >
b1010101 *
#860000
0$
1!
b0 #
b0 .
08
1;
b0 9
b110 (
b110 -
b110 >
b1010110 *
#870000
b111 (
b111 -
b111 >
b1010111 *
#880000
1$
0!
b1011 #
b1011 .
18
0;
b1011 9
b0 (
b0 -
b1011 '
b1011 ,
b1011 =
b0 >
b1011000 *
#890000
0$
1%
0!
b101 #
b101 .
08
17
b101 9
b1 (
b1 -
b1 >
b1011001 *
#900000
0%
1!
b0 #
b0 .
1;
07
b0 9
b10 (
b10 -
b10 >
b1011010 *
#910000
1$
0!
b1011 #
b1011 .
18
0;
b1011 9
b11 (
b11 -
b11 >
b1011011 *
#920000
0!
b1011 #
b1011 .
b1011 9
b100 (
b100 -
b100 >
b1011100 *
#930000
0!
b1111 #
b1111 .
b1111 9
b101 (
b101 -
b101 >
b1011101 *
#940000
0$
1!
b0 #
b0 .
08
1;
b0 9
b110 (
b110 -
b110 >
b1011110 *
#950000
b111 (
b111 -
b111 >
b1011111 *
#960000
1$
0!
b1100 #
b1100 .
18
0;
b1100 9
b0 (
b0 -
b1100 '
b1100 ,
b1100 =
b0 >
b1100000 *
#970000
0$
1%
0!
b100 #
b100 .
08
17
b100 9
b1 (
b1 -
b1 >
b1100001 *
#980000
0%
1!
b0 #
b0 .
1;
07
b0 9
b10 (
b10 -
b10 >
b1100010 *
#990000
1$
0!
b1100 #
b1100 .
18
0;
b1100 9
b11 (
b11 -
b11 >
b1100011 *
#1000000
0!
b1100 #
b1100 .
b1100 9
b100 (
b100 -
b100 >
b1100100 *
#1010000
0!
b1111 #
b1111 .
b1111 9
b101 (
b101 -
b101 >
b1100101 *
#1020000
0$
1!
b0 #
b0 .
08
1;
b0 9
b110 (
b110 -
b110 >
b1100110 *
#1030000
b111 (
b111 -
b111 >
b1100111 *
#1040000
1$
0!
b1101 #
b1101 .
18
0;
b1101 9
b0 (
b0 -
b1101 '
b1101 ,
b1101 =
b0 >
b1101000 *
#1050000
0$
1%
0!
b11 #
b11 .
08
17
b11 9
b1 (
b1 -
b1 >
b1101001 *
#1060000
0%
1!
b0 #
b0 .
1;
07
b0 9
b10 (
b10 -
b10 >
b1101010 *
#1070000
1$
0!
b1101 #
b1101 .
18
0;
b1101 9
b11 (
b11 -
b11 >
b1101011 *
#1080000
0!
b1101 #
b1101 .
b1101 9
b100 (
b100 -
b100 >
b1101100 *
#1090000
0!
b1111 #
b1111 .
b1111 9
b101 (
b101 -
b101 >
b1101101 *
#1100000
0$
1!
b0 #
b0 .
08
1;
b0 9
b110 (
b110 -
b110 >
b1101110 *
#1110000
b111 (
b111 -
b111 >
b1101111 *
#1120000
1$
0!
b1110 #
b1110 .
18
0;
b1110 9
b0 (
b0 -
b1110 '
b1110 ,
b1110 =
b0 >
b1110000 *
#1130000
0$
1%
0!
b10 #
b10 .
08
17
b10 9
b1 (
b1 -
b1 >
b1110001 *
#1140000
0%
1!
b0 #
b0 .
1;
07
b0 9
b10 (
b10 -
b10 >
b1110010 *
#1150000
1$
0!
b1110 #
b1110 .
18
0;
b1110 9
b11 (
b11 -
b11 >
b1110011 *
#1160000
0!
b1110 #
b1110 .
b1110 9
b100 (
b100 -
b100 >
b1110100 *
#1170000
0!
b1111 #
b1111 .
b1111 9
b101 (
b101 -
b101 >
b1110101 *
#1180000
0$
1!
b0 #
b0 .
08
1;
b0 9
b110 (
b110 -
b110 >
b1110110 *
#1190000
b111 (
b111 -
b111 >
b1110111 *
#1200000
1$
0!
b1111 #
b1111 .
18
0;
b1111 9
b0 (
b0 -
b1111 '
b1111 ,
b1111 =
b0 >
b1111000 *
#1210000
0$
1%
0!
b1 #
b1 .
08
17
b1 9
b1 (
b1 -
b1 >
b1111001 *
#1220000
0%
1!
b0 #
b0 .
1;
07
b0 9
b10 (
b10 -
b10 >
b1111010 *
#1230000
1$
0!
b1111 #
b1111 .
18
0;
b1111 9
b11 (
b11 -
b11 >
b1111011 *
#1240000
0!
b1111 #
b1111 .
b1111 9
b100 (
b100 -
b100 >
b1111100 *
#1250000
0!
b1111 #
b1111 .
b1111 9
b101 (
b101 -
b101 >
b1111101 *
#1260000
0$
1!
b0 #
b0 .
08
1;
b0 9
b110 (
b110 -
b110 >
b1111110 *
#1270000
b111 (
b111 -
b111 >
b1111111 *
#1280000
0!
b1 #
b1 .
0;
b1 9
b0 (
b0 -
b0 '
b0 ,
b1 &
b1 +
b1 <
b0 =
b0 >
b10000000 *
#1290000
0!
b1 #
b1 .
b1 9
b1 (
b1 -
b1 >
b10000001 *
#1300000
1!
b0 #
b0 .
1;
b0 9
b10 (
b10 -
b10 >
b10000010 *
#1310000
0!
b1 #
b1 .
0;
b1 9
b11 (
b11 -
b11 >
b10000011 *
#1320000
0!
b1 #
b1 .
b1 9
b100 (
b100 -
b100 >
b10000100 *
#1330000
1$
0!
b1110 #
b1110 .
18
b1110 9
b101 (
b101 -
b101 >
b10000101 *
#1340000
0$
0!
b10 #
b10 .
08
b10 9
b110 (
b110 -
b110 >
b10000110 *
#1350000
1%
1!
b0 #
b0 .
1;
17
b0 9
b111 (
b111 -
b111 >
b10000111 *
#1360000
0!
b10 #
b10 .
0%
0;
b10 9
07
b0 (
b0 -
b1 '
b1 ,
b1 =
b0 >
b10001000 *
#1370000
1!
b0 #
b0 .
1;
b0 9
b1 (
b1 -
b1 >
b10001001 *
#1380000
0!
b1 #
b1 .
0;
b1 9
b10 (
b10 -
b10 >
b10001010 *
#1390000
0!
b1 #
b1 .
b1 9
b11 (
b11 -
b11 >
b10001011 *
#1400000
1!
b0 #
b0 .
1;
b0 9
b100 (
b100 -
b100 >
b10001100 *
#1410000
1$
0!
b1110 #
b1110 .
18
0;
b1110 9
b101 (
b101 -
b101 >
b10001101 *
#1420000
0$
0!
b10 #
b10 .
08
b10 9
b110 (
b110 -
b110 >
b10001110 *
#1430000
1%
1!
b0 #
b0 .
1;
17
b0 9
b111 (
b111 -
b111 >
b10001111 *
#1440000
0!
b11 #
b11 .
0%
0;
b11 9
07
b0 (
b0 -
b10 '
b10 ,
b10 =
b0 >
b10010000 *
#1450000
1$
1%
0!
b1111 #
b1111 .
18
17
b1111 9
b1 (
b1 -
b1 >
b10010001 *
#1460000
0$
0%
1!
b0 #
b0 .
08
1;
07
b0 9
b10 (
b10 -
b10 >
b10010010 *
#1470000
0!
b11 #
b11 .
0;
b11 9
b11 (
b11 -
b11 >
b10010011 *
#1480000
0!
b11 #
b11 .
b11 9
b100 (
b100 -
b100 >
b10010100 *
#1490000
1$
0!
b1110 #
b1110 .
18
b1110 9
b101 (
b101 -
b101 >
b10010101 *
#1500000
0$
0!
b10 #
b10 .
08
b10 9
b110 (
b110 -
b110 >
b10010110 *
#1510000
1%
1!
b0 #
b0 .
1;
17
b0 9
b111 (
b111 -
b111 >
b10010111 *
#1520000
0!
b100 #
b100 .
0%
0;
b100 9
07
b0 (
b0 -
b11 '
b11 ,
b11 =
b0 >
b10011000 *
#1530000
1$
1%
0!
b1110 #
b1110 .
18
17
b1110 9
b1 (
b1 -
b1 >
b10011001 *
#1540000
0$
0%
0!
b1 #
b1 .
08
07
b1 9
b10 (
b10 -
b10 >
b10011010 *
#1550000
0!
b11 #
b11 .
b11 9
b11 (
b11 -
b11 >
b10011011 *
#1560000
0!
b10 #
b10 .
b10 9
b100 (
b100 -
b100 >
b10011100 *
#1570000
1$
0!
b1110 #
b1110 .
18
b1110 9
b101 (
b101 -
b101 >
b10011101 *
#1580000
0$
0!
b10 #
b10 .
08
b10 9
b110 (
b110 -
b110 >
b10011110 *
#1590000
1%
1!
b0 #
b0 .
1;
17
b0 9
b111 (
b111 -
b111 >
b10011111 *
#1600000
0!
b101 #
b101 .
0%
0;
b101 9
07
b0 (
b0 -
b100 '
b100 ,
b100 =
b0 >
b10100000 *
#1610000
1$
1%
0!
b1101 #
b1101 .
18
17
b1101 9
b1 (
b1 -
b1 >
b10100001 *
#1620000
0$
0%
1!
b0 #
b0 .
08
1;
07
b0 9
b10 (
b10 -
b10 >
b10100010 *
#1630000
0!
b101 #
b101 .
0;
b101 9
b11 (
b11 -
b11 >
b10100011 *
#1640000
0!
b101 #
b101 .
b101 9
b100 (
b100 -
b100 >
b10100100 *
#1650000
1$
0!
b1110 #
b1110 .
18
b1110 9
b101 (
b101 -
b101 >
b10100101 *
#1660000
0$
0!
b10 #
b10 .
08
b10 9
b110 (
b110 -
b110 >
b10100110 *
#1670000
1%
1!
b0 #
b0 .
1;
17
b0 9
b111 (
b111 -
b111 >
b10100111 *
