digital_circuits/sequential_circuits/fsm/sequence_detector/s_0110/mealy/s_0110_overlapping/rtl/s_0110_overlapping.v
module s_0110_overlapping(
    input clk,
    input en,
    input areset_n,
    input in,
    output reg out
);
    parameter a=2'b00;
    parameter b=2'b01;
    parameter c=2'b10;
    parameter d=2'b11;

    reg [1:0] state, next;

    always @(posedge clk, negedge areset_n) begin
        if(~areset_n) begin
            state <= a;
        end
        else begin
            if (en) begin
                state <= next;
            end
            else begin
                state <= state;
            end
        end
    end

    always @(state, in) begin
        next = a;
        out = 1'b0;

        case (state)
            a: begin
                if(in) begin
                    next = a;
                    out = 0;
                end
                else begin
                    next = b;
                    out = 0;
                end
            end

            b: begin
                if(in) begin
                    next = c;
                    out = 0;
                end
                else begin
                    next = b;
                    out = 0;
                end
            end

            c: begin
                if(in) begin
                    next = d;
                    out = 0;
                end
                else begin
                    next = b;
                    out = 0;
                end
            end

            d: begin
                if(in) begin
                    next = a;
                    out = 0;
                end
                else begin
                    next = b;
                    out = 1;
                end
            end

            default: begin
                next = a;
                out = 0;
            end
        endcase
    end 

endmodule

digital_circuits/sequential_circuits/fsm/sequence_detector/s_0110/moore/s_0110_overlapping/tb/tb_s_0110_overlapping.v
`timescale 1ns/1ps

module tb_s_0110_overlapping;
    reg clk;
    reg en;
    reg areset_n;
    reg in;
    wire out;

    s_0110_overlapping dut (
        .clk(clk),
        .en(en),
        .areset_n(areset_n),
        .in(in),
        .out(out)
    );

    initial begin
        $dumpfile("waves/dump.vcd");
        $dumpvars(0,tb_s_0110_overlapping);
    end

    initial begin
        clk = 0;
        en =0;
        areset_n =0;
        in = 0;
        forever #5 clk = ~clk;
    end

    task check;
        input reg t_in;
        begin
            in = t_in;
            #1;
            $display("en = %b | areset_n = %b | in = %b | out = %b",en,areset_n,in,out);
        end
    endtask

    initial begin
        #3 en = 1;
        #3 areset_n = 1;
        @(negedge clk) check(0);
        @(negedge clk) check(0);
        @(negedge clk) check(1);
        @(negedge clk) check(1);
        @(negedge clk) check(1);
        @(negedge clk) check(0);
        @(negedge clk) check(1);
        @(negedge clk) check(1);
        @(negedge clk) check(0);
        @(negedge clk) check(1);
        @(negedge clk) check(1);
        @(negedge clk) check(0);
        @(negedge clk) check(0);


        #10; $finish;
    end
endmodule

digital_circuits/sequential_circuits/fsm/sequence_detector/s_0110/mealy/s_0110_overlapping/waves/dump.vcd
$date
	Thu Sep 17 09:39:42 2026
$end
$version
	Icarus Verilog
$end
$timescale
	1ps
$end
$scope module tb_s_0110_overlapping $end
$var wire 1 ! out $end
$var reg 1 " areset_n $end
$var reg 1 # clk $end
$var reg 1 $ en $end
$var reg 1 % in $end
$scope module dut $end
$var wire 1 " areset_n $end
$var wire 1 # clk $end
$var wire 1 $ en $end
$var wire 1 % in $end
$var parameter 2 & a $end
$var parameter 2 ' b $end
$var parameter 2 ( c $end
$var parameter 2 ) d $end
$var reg 2 * next [1:0] $end
$var reg 1 ! out $end
$var reg 2 + state [1:0] $end
$upscope $end
$scope task check $end
$var reg 1 , t_in $end
$upscope $end
$upscope $end
$enddefinitions $end
$comment Show the parameter values. $end
$dumpall
b11 )
b10 (
b1 '
b0 &
$end
#0
$dumpvars
x,
b0 +
b1 *
0%
0$
0#
0"
0!
$end
#3000
1$
#5000
1#
#6000
1"
#10000
0,
0#
#15000
b1 *
b1 +
1#
#20000
0#
#25000
1#
#30000
b10 *
1%
1,
0#
#35000
b11 *
b10 +
1#
#40000
0#
#45000
b0 *
b11 +
1#
#50000
0#
#55000
b0 +
1#
#60000
b1 *
0%
0,
0#
#65000
b1 *
b1 +
1#
#70000
b10 *
1%
1,
0#
#75000
b11 *
b10 +
1#
#80000
0#
#85000
b0 *
b11 +
1#
#90000
1!
b1 *
0%
0,
0#
#95000
0!
b1 *
b1 +
1#
#100000
b10 *
1%
1,
0#
#105000
b11 *
b10 +
1#
#110000
0#
#115000
b0 *
b11 +
1#
#120000
1!
b1 *
0%
0,
0#
#125000
0!
b1 *
b1 +
1#
