digital_circuits/sequential_circuits/counter/synchronous_counters/up_counter/mod_8/rtl/D.v
module D (
    input clk,
    input en,
    input areset_n,
    input d,
    output reg q
);

    always @(posedge clk, negedge areset_n) begin
        if(!areset_n) begin
            q <= 1'b0;
        end
        else if(en) begin
            q <= d;
        end
        else begin
            q <= q;
        end
    end

endmodule

digital_circuits/sequential_circuits/counter/ring/rtl/mux_D.v
module mux_D(
    input clk,
    input en,
    input areset_n,
    input p_in,
    input s_in,
    input load_shift,
    output reg out
);

    wire in;

    assign in = (load_shift)?p_in:s_in;

    D dff(
        .clk(clk),
        .en(en),
        .areset_n(areset_n),
        .d(in),
        .q(out)
    );

endmodule

digital_circuits/sequential_circuits/counter/ring/rtl/ring.v
module ring (
    input clk,
    input en,
    input areset_n,
    input load_shift,
    output [3:0] out
);

    wire [3:0] w , in;
    assign in = 4'b1000;
    assign out = w;

    mux_D u3(
        .clk(clk),
        .en(en),
        .areset_n(areset_n),
        .p_in(in[3]),
        .s_in(w[0]),
        .load_shift(load_shift),
        .out(w[3])
    );

    mux_D u2(
        .clk(clk),
        .en(en),
        .areset_n(areset_n),
        .p_in(in[2]),
        .s_in(w[3]),
        .load_shift(load_shift),
        .out(w[2])
    );

    mux_D u1(
        .clk(clk),
        .en(en),
        .areset_n(areset_n),
        .p_in(in[1]),
        .s_in(w[2]),
        .load_shift(load_shift),
        .out(w[1])
    );

    mux_D u0(
        .clk(clk),
        .en(en),
        .areset_n(areset_n),
        .p_in(in[0]),
        .s_in(w[1]),
        .load_shift(load_shift),
        .out(w[0])
    );

    
endmodule

digital_circuits/sequential_circuits/counter/ring/tb/tb_ring.v
`timescale 1ns/1ps

module tb_ring;

    reg clk;
    reg en;
    reg areset_n;
    reg load_shift;
    wire [3:0] out;

    ring dut (
        .clk(clk),
        .en(en),
        .areset_n(areset_n),
        .load_shift(load_shift),
        .out(out)
    );

    initial begin
        $dumpfile("waves/dump.vcd");
        $dumpvars(0,tb_ring);

    end

    initial begin
        clk = 0;
        en=0;
        areset_n =0;
        load_shift = 0;
        forever #5 clk = ~clk;
    end

    task check;
        begin
            $display("en = %b | areset_n = %b | out = %b",en,areset_n,out);
        end
    endtask

    initial begin
        #7 areset_n = 1;
        #7 en = 1;
        #7 load_shift=1;
        #7 load_shift = 0;
        #7;
        repeat (10) begin
            @(negedge clk) check();
        end 

        #10 $finish;
    end
endmodule

digital_circuits/sequential_circuits/counter/ring/waves/dump.vcd
$date
	Thu Sep 17 06:25:12 2026
$end
$version
	Icarus Verilog
$end
$timescale
	1ps
$end
$scope module tb_ring $end
$var wire 4 ! out [3:0] $end
$var reg 1 " areset_n $end
$var reg 1 # clk $end
$var reg 1 $ en $end
$var reg 1 % load_shift $end
$scope module dut $end
$var wire 1 " areset_n $end
$var wire 1 # clk $end
$var wire 1 $ en $end
$var wire 4 & in [3:0] $end
$var wire 1 % load_shift $end
$var wire 4 ' out [3:0] $end
$var wire 4 ( w [3:0] $end
$scope module u0 $end
$var wire 1 " areset_n $end
$var wire 1 # clk $end
$var wire 1 $ en $end
$var wire 1 % load_shift $end
$var wire 1 ) p_in $end
$var wire 1 * s_in $end
$var wire 1 + out $end
$var wire 1 , in $end
$scope module dff $end
$var wire 1 " areset_n $end
$var wire 1 # clk $end
$var wire 1 , d $end
$var wire 1 $ en $end
$var reg 1 + q $end
$upscope $end
$upscope $end
$scope module u1 $end
$var wire 1 " areset_n $end
$var wire 1 # clk $end
$var wire 1 $ en $end
$var wire 1 % load_shift $end
$var wire 1 - p_in $end
$var wire 1 . s_in $end
$var wire 1 / out $end
$var wire 1 0 in $end
$scope module dff $end
$var wire 1 " areset_n $end
$var wire 1 # clk $end
$var wire 1 0 d $end
$var wire 1 $ en $end
$var reg 1 / q $end
$upscope $end
$upscope $end
$scope module u2 $end
$var wire 1 " areset_n $end
$var wire 1 # clk $end
$var wire 1 $ en $end
$var wire 1 % load_shift $end
$var wire 1 1 p_in $end
$var wire 1 2 s_in $end
$var wire 1 3 out $end
$var wire 1 4 in $end
$scope module dff $end
$var wire 1 " areset_n $end
$var wire 1 # clk $end
$var wire 1 4 d $end
$var wire 1 $ en $end
$var reg 1 3 q $end
$upscope $end
$upscope $end
$scope module u3 $end
$var wire 1 " areset_n $end
$var wire 1 # clk $end
$var wire 1 $ en $end
$var wire 1 % load_shift $end
$var wire 1 5 p_in $end
$var wire 1 6 s_in $end
$var wire 1 7 out $end
$var wire 1 8 in $end
$scope module dff $end
$var wire 1 " areset_n $end
$var wire 1 # clk $end
$var wire 1 8 d $end
$var wire 1 $ en $end
$var reg 1 7 q $end
$upscope $end
$upscope $end
$upscope $end
$scope task check $end
$upscope $end
$upscope $end
$enddefinitions $end
$comment Show the parameter values. $end
$dumpall
$end
#0
$dumpvars
08
07
06
15
04
03
02
01
00
0/
0.
0-
0,
0+
0*
0)
b0 (
b0 '
b1000 &
0%
0$
0#
0"
b0 !
$end
#5000
1#
#7000
1"
#10000
0#
#14000
1$
#15000
1#
#20000
0#
#21000
18
1%
#25000
12
b1000 !
b1000 '
b1000 (
17
1#
#28000
14
08
0%
#30000
0#
#35000
04
10
02
1.
07
b100 !
b100 '
b100 (
13
1#
#40000
0#
#45000
1,
00
1*
0.
1/
b10 !
b10 '
b10 (
03
1#
#50000
0#
#55000
0,
18
0*
16
0/
b1 !
b1 '
b1 (
1+
1#
#60000
0#
#65000
08
14
06
12
0+
b1000 !
b1000 '
b1000 (
17
1#
#70000
0#
#75000
04
10
02
1.
07
b100 !
b100 '
b100 (
13
1#
#80000
0#
#85000
1,
00
1*
0.
1/
b10 !
b10 '
b10 (
03
1#
#90000
0#
#95000
0,
18
0*
16
0/
b1 !
b1 '
b1 (
1+
1#
#100000
0#
#105000
08
14
06
12
0+
b1000 !
b1000 '
b1000 (
17
1#
#110000
0#
#115000
04
10
02
1.
07
b100 !
b100 '
b100 (
13
1#
#120000
0#
#125000
1,
00
1*
0.
1/
b10 !
b10 '
b10 (
03
1#
#130000
0#
#135000
0,
18
0*
16
0/
b1 !
b1 '
b1 (
1+
1#
