digital_circuits/memories/rom/rtl/rom.v
module rom (
    input [3:0] addr,
    output reg [7:0] data
);


    always @(*) begin
        case (addr)
            0: data = 8'h3F;
            1: data = 8'h06;
            2: data = 8'h5B;
            3: data = 8'h4F;
            4: data = 8'h66;
            5: data = 8'h6D;
            6: data = 8'h7D;
            7: data = 8'h07;
            8: data = 8'h7F;
            9: data = 8'h6F;
            4'hA: data = 8'h77;
            4'hB: data = 8'h7C;
            4'hC: data = 8'h39;
            4'hD: data = 8'h5E;
            4'hE: data = 8'h79;
            4'hF: data = 8'h71;
            default: data = 8'h00;

        endcase
    end

endmodule

digital_circuits/memories/rom/tb/tb_rom.v
`timescale 1ns/1ps
module tb_rom;
    reg [3:0] addr;
    wire [7:0] data;
    reg [7:0] exp_data;

    integer PASS;
    integer FAIL;
    integer i;

    rom dut(
        .addr(addr),
        .data(data)
    );

    initial begin
        $dumpfile("waves/dump.vcd");
        $dumpvars(0,tb_rom);
    end

    task check;
        input [3:0] t_addr;
        begin
            addr = t_addr;
            case (t_addr)
            0: exp_data = 8'h3F;
            1: exp_data = 8'h06;
            2: exp_data = 8'h5B;
            3: exp_data = 8'h4F;
            4: exp_data = 8'h66;
            5: exp_data = 8'h6D;
            6: exp_data = 8'h7D;
            7: exp_data = 8'h07;
            8: exp_data = 8'h7F;
            9: exp_data = 8'h6F;
            4'hA: exp_data = 8'h77;
            4'hB: exp_data = 8'h7C;
            4'hC: exp_data = 8'h39;
            4'hD: exp_data = 8'h5E;
            4'hE: exp_data = 8'h79;
            4'hF: exp_data = 8'h71;
            default: exp_data = 8'h00;

        endcase
        #1;
        if(exp_data === data) begin
            $display("PASS | addr = %h | data = %h | exp_data = %h", addr, data, exp_data);
            PASS = PASS + 1;
        end
        else begin
            $display("FAIL | addr = %h | data = %h | exp_data = %h", addr, data, exp_data);
            FAIL = FAIL + 1;
        end
        end
    endtask

    initial begin
        PASS = 0;
        FAIL = 0;
        for(i=0;i<16;i=i+1) begin
            check(i);
            #5;
        end

        $display("SUMMARY");
        $display("PASS = %d",PASS);
        $display("FAIL = %d",FAIL);
        
        #20;
        $finish;
    end
endmodule

digital_circuits/memories/rom/waves/dump.vcd
$date
	Fri Oct  2 07:04:21 2026
$end
$version
	Icarus Verilog
$end
$timescale
	1ps
$end
$scope module tb_rom $end
$var wire 8 ! data [7:0] $end
$var reg 4 " addr [3:0] $end
$var reg 8 # exp_data [7:0] $end
$var integer 32 $ FAIL [31:0] $end
$var integer 32 % PASS [31:0] $end
$var integer 32 & i [31:0] $end
$scope module dut $end
$var wire 4 ' addr [3:0] $end
$var reg 8 ( data [7:0] $end
$upscope $end
$scope task check $end
$var reg 4 ) t_addr [3:0] $end
$upscope $end
$upscope $end
$enddefinitions $end
$comment Show the parameter values. $end
$dumpall
$end
#0
$dumpvars
b0 )
b111111 (
b0 '
b0 &
b0 %
b0 $
b111111 #
b0 "
b111111 !
$end
#1000
b1 %
#6000
b110 !
b110 (
b110 #
b1 "
b1 '
b1 )
b1 &
#7000
b10 %
#12000
b1011011 !
b1011011 (
b1011011 #
b10 "
b10 '
b10 )
b10 &
#13000
b11 %
#18000
b1001111 !
b1001111 (
b1001111 #
b11 "
b11 '
b11 )
b11 &
#19000
b100 %
#24000
b1100110 !
b1100110 (
b1100110 #
b100 "
b100 '
b100 )
b100 &
#25000
b101 %
#30000
b1101101 !
b1101101 (
b1101101 #
b101 "
b101 '
b101 )
b101 &
#31000
b110 %
#36000
b1111101 !
b1111101 (
b1111101 #
b110 "
b110 '
b110 )
b110 &
#37000
b111 %
#42000
b111 !
b111 (
b111 #
b111 "
b111 '
b111 )
b111 &
#43000
b1000 %
#48000
b1111111 !
b1111111 (
b1111111 #
b1000 "
b1000 '
b1000 )
b1000 &
#49000
b1001 %
#54000
b1101111 !
b1101111 (
b1101111 #
b1001 "
b1001 '
b1001 )
b1001 &
#55000
b1010 %
#60000
b1110111 !
b1110111 (
b1110111 #
b1010 "
b1010 '
b1010 )
b1010 &
#61000
b1011 %
#66000
b1111100 !
b1111100 (
b1111100 #
b1011 "
b1011 '
b1011 )
b1011 &
#67000
b1100 %
#72000
b111001 !
b111001 (
b111001 #
b1100 "
b1100 '
b1100 )
b1100 &
#73000
b1101 %
#78000
b1011110 !
b1011110 (
b1011110 #
b1101 "
b1101 '
b1101 )
b1101 &
#79000
b1110 %
#84000
b1111001 !
b1111001 (
b1111001 #
b1110 "
b1110 '
b1110 )
b1110 &
#85000
b1111 %
#90000
b1110001 !
b1110001 (
b1110001 #
b1111 "
b1111 '
b1111 )
b1111 &
#91000
b10000 %
#96000
b10000 &
