digital_circuits/memories/single_port_ram/rtl/single_port_ram.v
module single_port_ram (
    input clk,
    input we,
    input [3:0] addr,
    input [7:0] din,
    output reg [7:0] dout
);

    reg [7:0] mem [0:15];

    always @(posedge clk) begin
        if(we) begin
            mem[addr] <= din;
        end
        else begin
            dout <= mem[addr];
        end 
    
    end

endmodule

digital_circuits/memories/single_port_ram/tb/tb_single_port_ram.v
`timescale 1ns/1ps

module tb_single_port_ram;
    reg clk;
    reg we;
    reg [3:0] addr;
    reg [7:0] din;
    wire [7:0] dout;

    reg [7:0] t_mem [0:15];
    reg [7:0] exp_dout;
    integer PASS;
    integer FAIL;
    integer i;
    reg [7:0] pattern;

    single_port_ram dut(
        .clk(clk),
        .we(we),
        .addr(addr),
        .din(din),
        .dout(dout)
    );

    initial begin
        $dumpfile("waves/dump.vcd");
        $dumpvars(0,tb_single_port_ram);
    end

    initial begin
        clk = 0;
        we = 0;
        addr = 4'h0;
        din = 8'h00;
        exp_dout = 8'hxx;
        PASS = 0;
        FAIL = 0;

        pattern = 8'h00;

        forever #5 clk = ~clk;
    end


    task read;
        input [3:0] t_addr;
        begin
           
            @(negedge clk) begin
                we = 0;
                addr = t_addr;
                
            end
            

            @(posedge clk) begin
                exp_dout = t_mem[t_addr];
                #1;
                if(dout === exp_dout) begin
                    $display("PASS | addr = %h | dout = %h | exp_dout = %h", addr,dout, exp_dout);
                    PASS = PASS + 1;
                end
                else begin
                    $display("FAIL | addr = %h | dout = %h | exp_dout = %h", addr,dout, exp_dout);
                    FAIL = FAIL + 1;
                end
                
            end
        end

    endtask



    task write;
        input [3:0] t_addr;
        input [7:0] t_din;
        begin
            
            @(negedge clk) begin
                we = 1;
                addr = t_addr;
                din = t_din;
                
            end

         
            
            @(posedge clk) begin
                t_mem[t_addr] = t_din;
                // #1;
                // exp_dout = t_mem[t_addr];
                // #1;
                // if(dout == t_mem[t_addr]) begin
                //     $display("PASS | addr = %h | dout = %h | exp_dout = %h", addr,dout, exp_dout);
                //     PASS = PASS + 1;
                // end
                // else begin
                //     $display("FAIL | addr = %h | dout = %h | exp_dout = %h", addr,dout, exp_dout);
                //     FAIL = FAIL + 1;
                // end
            end
        end
    endtask

    initial begin
        #7;
        
        write (4'h0, 8'h00);
        for(i=1;i<16;i=i+1) begin
            case (i) 
                1: pattern = 8'hFF;
                2: pattern = 8'h0F;
                3: pattern = 8'hF0;
                4: pattern = 8'h88;
                5: pattern = 8'h11;
                6: pattern = 8'h99;
                7: pattern = 8'h10;
                8: pattern = 8'h01;
                default: pattern = 8'h20 + i;

            endcase
            write (i,pattern);
        end

        #10;
        for(i=0; i<16; i=i+1) begin
            read(i);
        end
        #10;
        write(4'h3,8'hCC);
        read(4'h3);
        read(4'h2);
        read(4'h4);

        #10;
        read(4'h6);
        write(4'h7, 8'h22);
        @(posedge clk) begin
            #1;
            if(dout === 8'h99) begin
                $display("PASS | addr = %h | dout = %h | exp_dout = %h", 6,dout, 8'h99);
                PASS = PASS + 1;
            end
            else begin
                $display("FAIL | addr = %h | dout = %h | exp_dout = %h", 6,dout, 8'h99);
                FAIL = FAIL + 1;
            end
        end

        $display("SUMMARY:");
        $display("PASS = %d",PASS);
        $display("FAIL = %d",FAIL);


        #20;
        $finish;
    end



endmodule

digital_circuits/memories/single_port_ram/waves/dump.vcd
$date
	Fri Oct  2 04:44:39 2026
$end
$version
	Icarus Verilog
$end
$timescale
	1ps
$end
$scope module tb_single_port_ram $end
$var wire 8 ! dout [7:0] $end
$var reg 4 " addr [3:0] $end
$var reg 1 # clk $end
$var reg 8 $ din [7:0] $end
$var reg 8 % exp_dout [7:0] $end
$var reg 8 & pattern [7:0] $end
$var reg 1 ' we $end
$var integer 32 ( FAIL [31:0] $end
$var integer 32 ) PASS [31:0] $end
$var integer 32 * i [31:0] $end
$scope module dut $end
$var wire 4 + addr [3:0] $end
$var wire 1 # clk $end
$var wire 8 , din [7:0] $end
$var wire 1 ' we $end
$var reg 8 - dout [7:0] $end
$upscope $end
$scope task read $end
$var reg 4 . t_addr [3:0] $end
$upscope $end
$scope task write $end
$var reg 4 / t_addr [3:0] $end
$var reg 8 0 t_din [7:0] $end
$upscope $end
$upscope $end
$enddefinitions $end
$comment Show the parameter values. $end
$dumpall
$end
#0
$dumpvars
bx 0
bx /
bx .
bx -
b0 ,
b0 +
bx *
b0 )
b0 (
0'
b0 &
bx %
b0 $
0#
b0 "
bx !
$end
#5000
1#
#7000
b0 0
b0 /
#10000
1'
0#
#15000
b11111111 0
b1 /
b11111111 &
b1 *
1#
#20000
b11111111 $
b11111111 ,
b1 "
b1 +
0#
#25000
b1111 0
b10 /
b1111 &
b10 *
1#
#30000
b1111 $
b1111 ,
b10 "
b10 +
0#
#35000
b11110000 0
b11 /
b11110000 &
b11 *
1#
#40000
b11110000 $
b11110000 ,
b11 "
b11 +
0#
#45000
b10001000 0
b100 /
b10001000 &
b100 *
1#
#50000
b10001000 $
b10001000 ,
b100 "
b100 +
0#
#55000
b10001 0
b101 /
b10001 &
b101 *
1#
#60000
b10001 $
b10001 ,
b101 "
b101 +
0#
#65000
b10011001 0
b110 /
b10011001 &
b110 *
1#
#70000
b10011001 $
b10011001 ,
b110 "
b110 +
0#
#75000
b10000 0
b111 /
b10000 &
b111 *
1#
#80000
b10000 $
b10000 ,
b111 "
b111 +
0#
#85000
b1 0
b1000 /
b1 &
b1000 *
1#
#90000
b1 $
b1 ,
b1000 "
b1000 +
0#
#95000
b101001 0
b1001 /
b101001 &
b1001 *
1#
#100000
b101001 $
b101001 ,
b1001 "
b1001 +
0#
#105000
b101010 0
b1010 /
b101010 &
b1010 *
1#
#110000
b101010 $
b101010 ,
b1010 "
b1010 +
0#
#115000
b101011 0
b1011 /
b101011 &
b1011 *
1#
#120000
b101011 $
b101011 ,
b1011 "
b1011 +
0#
#125000
b101100 0
b1100 /
b101100 &
b1100 *
1#
#130000
b101100 $
b101100 ,
b1100 "
b1100 +
0#
#135000
b101101 0
b1101 /
b101101 &
b1101 *
1#
#140000
b101101 $
b101101 ,
b1101 "
b1101 +
0#
#145000
b101110 0
b1110 /
b101110 &
b1110 *
1#
#150000
b101110 $
b101110 ,
b1110 "
b1110 +
0#
#155000
b101111 0
b1111 /
b101111 &
b1111 *
1#
#160000
b101111 $
b101111 ,
b1111 "
b1111 +
0#
#165000
b10000 *
1#
#170000
0#
#175000
1#
b0 .
b0 *
#180000
b0 "
b0 +
0'
0#
#185000
b0 !
b0 -
b0 %
1#
#186000
b1 .
b1 *
b1 )
#190000
b1 "
b1 +
0#
#195000
b11111111 !
b11111111 -
b11111111 %
1#
#196000
b10 .
b10 *
b10 )
#200000
b10 "
b10 +
0#
#205000
b1111 !
b1111 -
b1111 %
1#
#206000
b11 .
b11 *
b11 )
#210000
b11 "
b11 +
0#
#215000
b11110000 !
b11110000 -
b11110000 %
1#
#216000
b100 .
b100 *
b100 )
#220000
b100 "
b100 +
0#
#225000
b10001000 !
b10001000 -
b10001000 %
1#
#226000
b101 .
b101 *
b101 )
#230000
b101 "
b101 +
0#
#235000
b10001 !
b10001 -
b10001 %
1#
#236000
b110 .
b110 *
b110 )
#240000
b110 "
b110 +
0#
#245000
b10011001 !
b10011001 -
b10011001 %
1#
#246000
b111 .
b111 *
b111 )
#250000
b111 "
b111 +
0#
#255000
b10000 !
b10000 -
b10000 %
1#
#256000
b1000 .
b1000 *
b1000 )
#260000
b1000 "
b1000 +
0#
#265000
b1 !
b1 -
b1 %
1#
#266000
b1001 .
b1001 *
b1001 )
#270000
b1001 "
b1001 +
0#
#275000
b101001 !
b101001 -
b101001 %
1#
#276000
b1010 .
b1010 *
b1010 )
#280000
b1010 "
b1010 +
0#
#285000
b101010 !
b101010 -
b101010 %
1#
#286000
b1011 .
b1011 *
b1011 )
#290000
b1011 "
b1011 +
0#
#295000
b101011 !
b101011 -
b101011 %
1#
#296000
b1100 .
b1100 *
b1100 )
#300000
b1100 "
b1100 +
0#
#305000
b101100 !
b101100 -
b101100 %
1#
#306000
b1101 .
b1101 *
b1101 )
#310000
b1101 "
b1101 +
0#
#315000
b101101 !
b101101 -
b101101 %
1#
#316000
b1110 .
b1110 *
b1110 )
#320000
b1110 "
b1110 +
0#
#325000
b101110 !
b101110 -
b101110 %
1#
#326000
b1111 .
b1111 *
b1111 )
#330000
b1111 "
b1111 +
0#
#335000
b101111 !
b101111 -
b101111 %
1#
#336000
b10000 *
b10000 )
#340000
0#
#345000
1#
#346000
b11001100 0
b11 /
#350000
b11001100 $
b11001100 ,
b11 "
b11 +
1'
0#
#355000
b11 .
1#
#360000
0'
0#
#365000
b11001100 !
b11001100 -
b11001100 %
1#
#366000
b10 .
b10001 )
#370000
b10 "
b10 +
0#
#375000
b1111 !
b1111 -
b1111 %
1#
#376000
b100 .
b10010 )
#380000
b100 "
b100 +
0#
#385000
b10001000 !
b10001000 -
b10001000 %
1#
#386000
b10011 )
#390000
0#
#395000
1#
#396000
b110 .
#400000
b110 "
b110 +
0#
#405000
b10011001 !
b10011001 -
b10011001 %
1#
#406000
b100010 0
b111 /
b10100 )
#410000
b100010 $
b100010 ,
b111 "
b111 +
1'
0#
#415000
1#
#420000
0#
#425000
1#
#426000
b10101 )
