digital_circuits/combinational_circuit/full_adder/rtl/half_adder.v
module half_adder ( 
    input a,
    input b,
    output sum,
    output carry_out);

    assign sum = a^b;
    assign carry_out = a&b; 
endmodule

week2/combinational_circuit/full_adder/rtl/full_adder.v
module full_adder (
    input a,
    input b,
    input cin,
    output sum, 
    output carry_out
);
    wire sum1, c1, c2;
    half_adder ha1 (.a(a), .b(b), .sum(sum1), .carry_out(c1) );
    half_adder ha2 (.a(sum1), .b(cin), .sum(sum), .carry_out(c2) );
    assign carry_out = c1 | c2;
endmodule

week2/combinational_circuit/ripple_carry_adder/rtl/ripple_carry_adder.v
module ripple_carry_adder #(parameter N=4) (
    input [N-1:0] a, b,
    input cin,
    output [N-1:0] sum,
    output carry_out
); 

    wire [N:0] carry;
    assign carry[0] = cin;
    assign carry_out = carry[N];

    genvar i;

    generate
        for (i=0;i<N;i=i+1) begin : fa_stage
            full_adder dut (
                .a(a[i]),
                .b(b[i]),
                .cin(carry[i]),
                .sum(sum[i]),
                .carry_out(carry[i+1])
            );
        end
    endgenerate 


endmodule

week2/combinational_circuit/ripple_carry_adder/tb/tb_ripple_carry_adder.v
`timescale 1ns/1ps
module tb_ripple_carry_adder;

    reg [3:0] a, b;
    reg cin;
    wire [3:0] sum;
    wire carry_out;

    ripple_carry_adder #(.N(4)) dut (
        .a(a),
        .b(b),
        .cin(cin),
        .sum(sum),
        .carry_out(carry_out)
    );
    
    initial begin
        $dumpfile("waves/dump.vcd");
        $dumpvars(0,tb_ripple_carry_adder);
    end

    integer pass=0;
    integer fail=0;

    task exhaustive;
        reg [5:0] i,j;
        reg [1:0] k; 
        reg [3:0] exp_sum;
        reg exp_carry_out;
        begin
            for (i=0;i<16;i=i+1) begin
                a=i;
                for(j=0;j<16;j=j+1) begin
                    b=j;
                    for (k=0;k<2;k=k+1) begin
                        cin=k;
                        {exp_carry_out,exp_sum} = a + b + cin;
                        #10;
                        if(exp_sum === sum && exp_carry_out === carry_out) begin
                            $display("PASS: a=%b b=%b cin=%b | carry_out=%b sum=%b",a,b,cin,carry_out,sum);
                            pass=pass+1;

                        end
                        else begin
                            $display("FAIL: a=%b b=%b cin=%b | carry_out=%b sum=%b | exp_carry_out=%b exp_sum=%b",a,b,cin,carry_out,sum,exp_carry_out,exp_sum);
                            fail=fail+1;
                        end

                    end
                end
            end
            

        end

    endtask

    task check;
        input [3:0] t_a, t_b;
        input t_cin;
        reg [3:0] exp_sum;
        reg exp_carry_out;
        begin
            a=t_a; b=t_b; cin=t_cin;
            {exp_carry_out,exp_sum} = a+b+cin;
            #10;
            if(exp_sum === sum && exp_carry_out === carry_out) begin
                $display("PASS: a=%b b=%b cin=%b | carry_out=%b sum=%b",a,b,cin,carry_out,sum);
                    pass=pass+1;

            end
            else begin
                $display("FAIL: a=%b b=%b cin=%b | carry_out=%b sum=%b | exp_carry_out=%b exp_sum=%b",a,b,cin,carry_out,sum,exp_carry_out,exp_sum);
                fail=fail+1;
            end

        end

    endtask

    initial begin
        exhaustive();
        check(4'h0,4'h0,1'b0);
        check(4'h15,4'h15,1'b1);
        check(4'h15,4'h15,1'b0);
        check(4'h15,4'h15,1'b1);
        check(4'h15,4'h0,1'b0);
        check(4'h15,4'h1,1'b0);
        check(4'h1,4'h0,1'b0);
        check(4'h0,4'h1,1'b0);

        $display("Test Summary:");
        $display("PASS:%d",pass);
        $display("FAIL:%d",fail);
        $finish;

    end


endmodule

digital_circuits/combinational_circuit/ripple_carry_adder/waves/dump.vcd
$date
	Thu Jun  4 08:58:24 2026
$end
$version
	Icarus Verilog
$end
$timescale
	1ps
$end
$scope module tb_ripple_carry_adder $end
$var wire 4 ! sum [3:0] $end
$var wire 1 " carry_out $end
$var reg 4 # a [3:0] $end
$var reg 4 $ b [3:0] $end
$var reg 1 % cin $end
$var integer 32 & fail [31:0] $end
$var integer 32 ' pass [31:0] $end
$scope module dut $end
$var wire 4 ( a [3:0] $end
$var wire 4 ) b [3:0] $end
$var wire 1 % cin $end
$var wire 4 * sum [3:0] $end
$var wire 1 " carry_out $end
$var wire 5 + carry [4:0] $end
$var parameter 32 , N $end
$scope begin fa_stage[0] $end
$var parameter 2 - i $end
$scope module dut $end
$var wire 1 . a $end
$var wire 1 / b $end
$var wire 1 0 carry_out $end
$var wire 1 1 cin $end
$var wire 1 2 sum1 $end
$var wire 1 3 sum $end
$var wire 1 4 c2 $end
$var wire 1 5 c1 $end
$scope module ha1 $end
$var wire 1 . a $end
$var wire 1 / b $end
$var wire 1 5 carry_out $end
$var wire 1 2 sum $end
$upscope $end
$scope module ha2 $end
$var wire 1 2 a $end
$var wire 1 1 b $end
$var wire 1 4 carry_out $end
$var wire 1 3 sum $end
$upscope $end
$upscope $end
$upscope $end
$scope begin fa_stage[1] $end
$var parameter 2 6 i $end
$scope module dut $end
$var wire 1 7 a $end
$var wire 1 8 b $end
$var wire 1 9 carry_out $end
$var wire 1 : cin $end
$var wire 1 ; sum1 $end
$var wire 1 < sum $end
$var wire 1 = c2 $end
$var wire 1 > c1 $end
$scope module ha1 $end
$var wire 1 7 a $end
$var wire 1 8 b $end
$var wire 1 > carry_out $end
$var wire 1 ; sum $end
$upscope $end
$scope module ha2 $end
$var wire 1 ; a $end
$var wire 1 : b $end
$var wire 1 = carry_out $end
$var wire 1 < sum $end
$upscope $end
$upscope $end
$upscope $end
$scope begin fa_stage[2] $end
$var parameter 3 ? i $end
$scope module dut $end
$var wire 1 @ a $end
$var wire 1 A b $end
$var wire 1 B carry_out $end
$var wire 1 C cin $end
$var wire 1 D sum1 $end
$var wire 1 E sum $end
$var wire 1 F c2 $end
$var wire 1 G c1 $end
$scope module ha1 $end
$var wire 1 @ a $end
$var wire 1 A b $end
$var wire 1 G carry_out $end
$var wire 1 D sum $end
$upscope $end
$scope module ha2 $end
$var wire 1 D a $end
$var wire 1 C b $end
$var wire 1 F carry_out $end
$var wire 1 E sum $end
$upscope $end
$upscope $end
$upscope $end
$scope begin fa_stage[3] $end
$var parameter 3 H i $end
$scope module dut $end
$var wire 1 I a $end
$var wire 1 J b $end
$var wire 1 K carry_out $end
$var wire 1 L cin $end
$var wire 1 M sum1 $end
$var wire 1 N sum $end
$var wire 1 O c2 $end
$var wire 1 P c1 $end
$scope module ha1 $end
$var wire 1 I a $end
$var wire 1 J b $end
$var wire 1 P carry_out $end
$var wire 1 M sum $end
$upscope $end
$scope module ha2 $end
$var wire 1 M a $end
$var wire 1 L b $end
$var wire 1 O carry_out $end
$var wire 1 N sum $end
$upscope $end
$upscope $end
$upscope $end
$upscope $end
$scope task check $end
$var reg 1 Q exp_carry_out $end
$var reg 4 R exp_sum [3:0] $end
$var reg 4 S t_a [3:0] $end
$var reg 4 T t_b [3:0] $end
$var reg 1 U t_cin $end
$upscope $end
$scope task exhaustive $end
$var reg 1 V exp_carry_out $end
$var reg 4 W exp_sum [3:0] $end
$var reg 6 X i [5:0] $end
$var reg 6 Y j [5:0] $end
$var reg 2 Z k [1:0] $end
$upscope $end
$upscope $end
$enddefinitions $end
$comment Show the parameter values. $end
$dumpall
b11 H
b10 ?
b1 6
b0 -
b100 ,
$end
#0
$dumpvars
b0 Z
b0 Y
b0 X
b0 W
0V
xU
bx T
bx S
bx R
xQ
0P
0O
0N
0M
0L
0K
0J
0I
0G
0F
0E
0D
0C
0B
0A
0@
0>
0=
0<
0;
0:
09
08
07
05
04
03
02
01
00
0/
0.
b0 +
b0 *
b0 )
b0 (
b0 '
b0 &
0%
b0 $
b0 #
0"
b0 !
$end
#10000
b1 !
b1 *
13
11
b1 W
b1 +
1%
b1 Z
b1 '
#20000
12
01
1/
b0 +
0%
b1 $
b1 )
b1 Y
b0 Z
b10 '
#30000
1<
1:
10
b10 !
b10 *
03
14
11
b10 W
b11 +
1%
b1 Z
b11 '
#40000
0E
0C
0:
09
00
b10 !
b10 *
1<
0=
04
02
1;
01
0/
18
b0 +
0%
b10 $
b10 )
b10 Y
b0 Z
b100 '
#50000
b11 !
b11 *
13
11
b11 W
b1 +
1%
b1 Z
b101 '
#60000
12
01
1/
b0 +
0%
b11 $
b11 )
b11 Y
b0 Z
b110 '
#70000
1E
1C
19
0<
1=
1:
10
b100 !
b100 *
03
14
11
b100 W
b111 +
1%
b1 Z
b111 '
#80000
0N
0C
0L
0:
09
0B
00
0<
0=
b100 !
b100 *
1E
0F
04
02
0;
1D
01
0/
08
1A
b0 +
0%
b100 $
b100 )
b100 Y
b0 Z
b1000 '
#90000
b101 !
b101 *
13
11
b101 W
b1 +
1%
b1 Z
b1001 '
#100000
12
01
1/
b0 +
0%
b101 $
b101 )
b101 Y
b0 Z
b1010 '
#110000
1<
1:
10
b110 !
b110 *
03
14
11
b110 W
b11 +
1%
b1 Z
b1011 '
#120000
0N
0L
0B
1E
0F
0C
0:
09
00
b110 !
b110 *
1<
0=
04
02
1;
01
0/
18
b0 +
0%
b110 $
b110 )
b110 Y
b0 Z
b1100 '
#130000
b111 !
b111 *
13
11
b111 W
b1 +
1%
b1 Z
b1101 '
#140000
12
01
1/
b0 +
0%
b111 $
b111 )
b111 Y
b0 Z
b1110 '
#150000
1N
1L
1B
0E
1F
1C
19
0<
1=
1:
10
b1000 !
b1000 *
03
14
11
b1000 W
b1111 +
1%
b1 Z
b1111 '
#160000
0C
0L
0"
0:
09
0B
0K
00
0<
0=
0E
0F
b1000 !
b1000 *
1N
0O
04
02
0;
0D
1M
01
0/
08
0A
1J
b0 +
0%
b1000 $
b1000 )
b1000 Y
b0 Z
b10000 '
#170000
b1001 !
b1001 *
13
11
b1001 W
b1 +
1%
b1 Z
b10001 '
#180000
12
01
1/
b0 +
0%
b1001 $
b1001 )
b1001 Y
b0 Z
b10010 '
#190000
1<
1:
10
b1010 !
b1010 *
03
14
11
b1010 W
b11 +
1%
b1 Z
b10011 '
#200000
0E
0C
0:
09
00
b1010 !
b1010 *
1<
0=
04
02
1;
01
0/
18
b0 +
0%
b1010 $
b1010 )
b1010 Y
b0 Z
b10100 '
#210000
b1011 !
b1011 *
13
11
b1011 W
b1 +
1%
b1 Z
b10101 '
#220000
12
01
1/
b0 +
0%
b1011 $
b1011 )
b1011 Y
b0 Z
b10110 '
#230000
1E
1C
19
0<
1=
1:
10
b1100 !
b1100 *
03
14
11
b1100 W
b111 +
1%
b1 Z
b10111 '
#240000
0"
0K
1N
0O
0C
0L
0:
09
0B
00
0<
0=
b1100 !
b1100 *
1E
0F
04
02
0;
1D
01
0/
08
1A
b0 +
0%
b1100 $
b1100 )
b1100 Y
b0 Z
b11000 '
#250000
b1101 !
b1101 *
13
11
b1101 W
b1 +
1%
b1 Z
b11001 '
#260000
12
01
1/
b0 +
0%
b1101 $
b1101 )
b1101 Y
b0 Z
b11010 '
#270000
1<
1:
10
b1110 !
b1110 *
03
14
11
b1110 W
b11 +
1%
b1 Z
b11011 '
#280000
0"
0K
1N
0O
0L
0B
1E
0F
0C
0:
09
00
b1110 !
b1110 *
1<
0=
04
02
1;
01
0/
18
b0 +
0%
b1110 $
b1110 )
b1110 Y
b0 Z
b11100 '
#290000
b1111 !
b1111 *
13
11
b1111 W
b1 +
1%
b1 Z
b11101 '
#300000
12
01
1/
b0 +
0%
b1111 $
b1111 )
b1111 Y
b0 Z
b11110 '
#310000
1"
1K
0N
1O
1L
1B
0E
1F
1C
19
0<
1=
1:
10
b0 !
b0 *
03
14
11
1V
b0 W
b11111 +
1%
b1 Z
b11111 '
#320000
0C
0L
0"
0:
09
0B
0K
00
0<
0=
0E
0F
0N
0O
b1 !
b1 *
13
04
0;
0D
0M
01
0/
08
0A
0J
1.
0V
b1 W
b0 +
0%
b0 $
b0 )
b1 #
b1 (
b1 X
b0 Y
b0 Z
b100000 '
#330000
1<
1:
10
b10 !
b10 *
03
14
11
b10 W
b11 +
1%
b1 Z
b100001 '
#340000
04
02
15
01
1/
b10 +
0%
b1 $
b1 )
b1 Y
b0 Z
b100010 '
#350000
b11 !
b11 *
13
11
b11 W
b11 +
1%
b1 Z
b100011 '
#360000
0E
0C
0:
09
00
b11 !
b11 *
1<
0=
12
05
1;
01
0/
18
b0 +
0%
b10 $
b10 )
b10 Y
b0 Z
b100100 '
#370000
1E
1C
19
0<
1=
1:
10
b100 !
b100 *
03
14
11
b100 W
b111 +
1%
b1 Z
b100101 '
#380000
04
02
15
01
1/
b110 +
0%
b11 $
b11 )
b11 Y
b0 Z
b100110 '
#390000
b101 !
b101 *
13
11
b101 W
b111 +
1%
b1 Z
b100111 '
#400000
0N
0C
0L
0:
09
0B
00
0<
0=
b101 !
b101 *
1E
0F
12
05
0;
1D
01
0/
08
1A
b0 +
0%
b100 $
b100 )
b100 Y
b0 Z
b101000 '
#410000
1<
1:
10
b110 !
b110 *
03
14
11
b110 W
b11 +
1%
b1 Z
b101001 '
#420000
04
02
15
01
1/
b10 +
0%
b101 $
b101 )
b101 Y
b0 Z
b101010 '
#430000
b111 !
b111 *
13
11
b111 W
b11 +
1%
b1 Z
b101011 '
#440000
0N
0L
0B
1E
0F
0C
0:
09
00
b111 !
b111 *
1<
0=
12
05
1;
01
0/
18
b0 +
0%
b110 $
b110 )
b110 Y
b0 Z
b101100 '
#450000
1N
1L
1B
0E
1F
1C
19
0<
1=
1:
10
b1000 !
b1000 *
03
14
11
b1000 W
b1111 +
1%
b1 Z
b101101 '
#460000
04
02
15
01
1/
b1110 +
0%
b111 $
b111 )
b111 Y
b0 Z
b101110 '
#470000
b1001 !
b1001 *
13
11
b1001 W
b1111 +
1%
b1 Z
b101111 '
#480000
0C
0L
0"
0:
09
0B
0K
00
0<
0=
0E
0F
b1001 !
b1001 *
1N
0O
12
05
0;
0D
1M
01
0/
08
0A
1J
b0 +
0%
b1000 $
b1000 )
b1000 Y
b0 Z
b110000 '
#490000
1<
1:
10
b1010 !
b1010 *
03
14
11
b1010 W
b11 +
1%
b1 Z
b110001 '
#500000
04
02
15
01
1/
b10 +
0%
b1001 $
b1001 )
b1001 Y
b0 Z
b110010 '
#510000
b1011 !
b1011 *
13
11
b1011 W
b11 +
1%
b1 Z
b110011 '
#520000
0E
0C
0:
09
00
b1011 !
b1011 *
1<
0=
12
05
1;
01
0/
18
b0 +
0%
b1010 $
b1010 )
b1010 Y
b0 Z
b110100 '
#530000
1E
1C
19
0<
1=
1:
10
b1100 !
b1100 *
03
14
11
b1100 W
b111 +
1%
b1 Z
b110101 '
#540000
04
02
15
01
1/
b110 +
0%
b1011 $
b1011 )
b1011 Y
b0 Z
b110110 '
#550000
b1101 !
b1101 *
13
11
b1101 W
b111 +
1%
b1 Z
b110111 '
#560000
0"
0K
1N
0O
0C
0L
0:
09
0B
00
0<
0=
b1101 !
b1101 *
1E
0F
12
05
0;
1D
01
0/
08
1A
b0 +
0%
b1100 $
b1100 )
b1100 Y
b0 Z
b111000 '
#570000
1<
1:
10
b1110 !
b1110 *
03
14
11
b1110 W
b11 +
1%
b1 Z
b111001 '
#580000
04
02
15
01
1/
b10 +
0%
b1101 $
b1101 )
b1101 Y
b0 Z
b111010 '
#590000
b1111 !
b1111 *
13
11
b1111 W
b11 +
1%
b1 Z
b111011 '
#600000
0"
0K
1N
0O
0L
0B
1E
0F
0C
0:
09
00
b1111 !
b1111 *
1<
0=
12
05
1;
01
0/
18
b0 +
0%
b1110 $
b1110 )
b1110 Y
b0 Z
b111100 '
#610000
1"
1K
0N
1O
1L
1B
0E
1F
1C
19
0<
1=
1:
10
b0 !
b0 *
03
14
11
1V
b0 W
b11111 +
1%
b1 Z
b111101 '
#620000
04
02
15
01
1/
b11110 +
0%
b1111 $
b1111 )
b1111 Y
b0 Z
b111110 '
#630000
b1 !
b1 *
13
11
b1 W
b11111 +
1%
b1 Z
b111111 '
#640000
0C
09
0L
0"
1<
0=
0B
0K
0:
0E
0F
0N
0O
00
b10 !
b10 *
03
0D
0M
05
01
0/
08
0A
0J
0.
17
0V
b10 W
b0 +
0%
b0 $
b0 )
b10 #
b10 (
b10 X
b0 Y
b0 Z
b1000000 '
#650000
b11 !
b11 *
13
11
b11 W
b1 +
1%
b1 Z
b1000001 '
#660000
12
01
1/
b0 +
0%
b1 $
b1 )
b1 Y
b0 Z
b1000010 '
#670000
1E
1C
19
0<
1=
1:
10
b100 !
b100 *
03
14
11
b100 W
b111 +
1%
b1 Z
b1000011 '
#680000
0:
00
b100 !
b100 *
0<
0=
04
02
0;
1>
01
0/
18
b100 +
0%
b10 $
b10 )
b10 Y
b0 Z
b1000100 '
#690000
b101 !
b101 *
13
11
b101 W
b101 +
1%
b1 Z
b1000101 '
#700000
12
01
1/
b100 +
0%
b11 $
b11 )
b11 Y
b0 Z
b1000110 '
#710000
1<
1:
10
b110 !
b110 *
03
14
11
b110 W
b111 +
1%
b1 Z
b1000111 '
#720000
0N
0L
0:
0C
0B
00
1<
0=
09
b110 !
b110 *
1E
0F
04
02
1;
0>
1D
01
0/
08
1A
b0 +
0%
b100 $
b100 )
b100 Y
b0 Z
b1001000 '
#730000
b111 !
b111 *
13
11
b111 W
b1 +
1%
b1 Z
b1001001 '
#740000
12
01
1/
b0 +
0%
b101 $
b101 )
b101 Y
b0 Z
b1001010 '
#750000
1N
1L
1B
0E
1F
1C
19
0<
1=
1:
10
b1000 !
b1000 *
03
14
11
b1000 W
b1111 +
1%
b1 Z
b1001011 '
#760000
0:
00
b1000 !
b1000 *
0<
0=
04
02
0;
1>
01
0/
18
b1100 +
0%
b110 $
b110 )
b110 Y
b0 Z
b1001100 '
#770000
b1001 !
b1001 *
13
11
b1001 W
b1101 +
1%
b1 Z
b1001101 '
#780000
12
01
1/
b1100 +
0%
b111 $
b111 )
b111 Y
b0 Z
b1001110 '
#790000
1<
1:
10
b1010 !
b1010 *
03
14
11
b1010 W
b1111 +
1%
b1 Z
b1001111 '
#800000
0L
0"
0:
0C
0B
0K
00
1<
0=
09
0E
0F
b1010 !
b1010 *
1N
0O
04
02
1;
0>
0D
1M
01
0/
08
0A
1J
b0 +
0%
b1000 $
b1000 )
b1000 Y
b0 Z
b1010000 '
#810000
b1011 !
b1011 *
13
11
b1011 W
b1 +
1%
b1 Z
b1010001 '
#820000
12
01
1/
b0 +
0%
b1001 $
b1001 )
b1001 Y
b0 Z
b1010010 '
#830000
1E
1C
19
0<
1=
1:
10
b1100 !
b1100 *
03
14
11
b1100 W
b111 +
1%
b1 Z
b1010011 '
#840000
0:
00
b1100 !
b1100 *
0<
0=
04
02
0;
1>
01
0/
18
b100 +
0%
b1010 $
b1010 )
b1010 Y
b0 Z
b1010100 '
#850000
b1101 !
b1101 *
13
11
b1101 W
b101 +
1%
b1 Z
b1010101 '
#860000
12
01
1/
b100 +
0%
b1011 $
b1011 )
b1011 Y
b0 Z
b1010110 '
#870000
1<
1:
10
b1110 !
b1110 *
03
14
11
b1110 W
b111 +
1%
b1 Z
b1010111 '
#880000
0"
0K
1N
0O
0L
0:
0C
0B
00
1<
0=
09
b1110 !
b1110 *
1E
0F
04
02
1;
0>
1D
01
0/
08
1A
b0 +
0%
b1100 $
b1100 )
b1100 Y
b0 Z
b1011000 '
#890000
b1111 !
b1111 *
13
11
b1111 W
b1 +
1%
b1 Z
b1011001 '
#900000
12
01
1/
b0 +
0%
b1101 $
b1101 )
b1101 Y
b0 Z
b1011010 '
#910000
1"
1K
0N
1O
1L
1B
0E
1F
1C
19
0<
1=
1:
10
b0 !
b0 *
03
14
11
1V
b0 W
b11111 +
1%
b1 Z
b1011011 '
#920000
0:
00
b0 !
b0 *
0<
0=
04
02
0;
1>
01
0/
18
b11100 +
0%
b1110 $
b1110 )
b1110 Y
b0 Z
b1011100 '
#930000
b1 !
b1 *
13
11
b1 W
b11101 +
1%
b1 Z
b1011101 '
#940000
12
01
1/
b11100 +
0%
b1111 $
b1111 )
b1111 Y
b0 Z
b1011110 '
#950000
1<
1:
10
b10 !
b10 *
03
14
11
b10 W
b11111 +
1%
b1 Z
b1011111 '
#960000
0L
0"
0:
0C
0B
0K
00
1<
0=
09
0E
0F
0N
0O
b11 !
b11 *
13
04
1;
0>
0D
0M
01
0/
08
0A
0J
1.
0V
b11 W
b0 +
0%
b0 $
b0 )
b11 #
b11 (
b11 X
b0 Y
b0 Z
b1100000 '
#970000
1E
1C
19
0<
1=
1:
10
b100 !
b100 *
03
14
11
b100 W
b111 +
1%
b1 Z
b1100001 '
#980000
04
02
15
01
1/
b110 +
0%
b1 $
b1 )
b1 Y
b0 Z
b1100010 '
#990000
b101 !
b101 *
13
11
b101 W
b111 +
1%
b1 Z
b1100011 '
#1000000
0:
00
b101 !
b101 *
0<
0=
12
05
0;
1>
01
0/
18
b100 +
0%
b10 $
b10 )
b10 Y
b0 Z
b1100100 '
#1010000
1<
1:
10
b110 !
b110 *
03
14
11
b110 W
b111 +
1%
b1 Z
b1100101 '
#1020000
04
02
15
01
1/
b110 +
0%
b11 $
b11 )
b11 Y
b0 Z
b1100110 '
#1030000
b111 !
b111 *
13
11
b111 W
b111 +
1%
b1 Z
b1100111 '
#1040000
0N
0L
0:
0C
0B
00
1<
0=
09
b111 !
b111 *
1E
0F
12
05
1;
0>
1D
01
0/
08
1A
b0 +
0%
b100 $
b100 )
b100 Y
b0 Z
b1101000 '
#1050000
1N
1L
1B
0E
1F
1C
19
0<
1=
1:
10
b1000 !
b1000 *
03
14
11
b1000 W
b1111 +
1%
b1 Z
b1101001 '
#1060000
04
02
15
01
1/
b1110 +
0%
b101 $
b101 )
b101 Y
b0 Z
b1101010 '
#1070000
b1001 !
b1001 *
13
11
b1001 W
b1111 +
1%
b1 Z
b1101011 '
#1080000
0:
00
b1001 !
b1001 *
0<
0=
12
05
0;
1>
01
0/
18
b1100 +
0%
b110 $
b110 )
b110 Y
b0 Z
b1101100 '
#1090000
1<
1:
10
b1010 !
b1010 *
03
14
11
b1010 W
b1111 +
1%
b1 Z
b1101101 '
#1100000
04
02
15
01
1/
b1110 +
0%
b111 $
b111 )
b111 Y
b0 Z
b1101110 '
#1110000
b1011 !
b1011 *
13
11
b1011 W
b1111 +
1%
b1 Z
b1101111 '
#1120000
0L
0"
0:
0C
0B
0K
00
1<
0=
09
0E
0F
b1011 !
b1011 *
1N
0O
12
05
1;
0>
0D
1M
01
0/
08
0A
1J
b0 +
0%
b1000 $
b1000 )
b1000 Y
b0 Z
b1110000 '
#1130000
1E
1C
19
0<
1=
1:
10
b1100 !
b1100 *
03
14
11
b1100 W
b111 +
1%
b1 Z
b1110001 '
#1140000
04
02
15
01
1/
b110 +
0%
b1001 $
b1001 )
b1001 Y
b0 Z
b1110010 '
#1150000
b1101 !
b1101 *
13
11
b1101 W
b111 +
1%
b1 Z
b1110011 '
#1160000
0:
00
b1101 !
b1101 *
0<
0=
12
05
0;
1>
01
0/
18
b100 +
0%
b1010 $
b1010 )
b1010 Y
b0 Z
b1110100 '
#1170000
1<
1:
10
b1110 !
b1110 *
03
14
11
b1110 W
b111 +
1%
b1 Z
b1110101 '
#1180000
04
02
15
01
1/
b110 +
0%
b1011 $
b1011 )
b1011 Y
b0 Z
b1110110 '
#1190000
b1111 !
b1111 *
13
11
b1111 W
b111 +
1%
b1 Z
b1110111 '
#1200000
0"
0K
1N
0O
0L
0:
0C
0B
00
1<
0=
09
b1111 !
b1111 *
1E
0F
12
05
1;
0>
1D
01
0/
08
1A
b0 +
0%
b1100 $
b1100 )
b1100 Y
b0 Z
b1111000 '
#1210000
1"
1K
0N
1O
1L
1B
0E
1F
1C
19
0<
1=
1:
10
b0 !
b0 *
03
14
11
1V
b0 W
b11111 +
1%
b1 Z
b1111001 '
#1220000
04
02
15
01
1/
b11110 +
0%
b1101 $
b1101 )
b1101 Y
b0 Z
b1111010 '
#1230000
b1 !
b1 *
13
11
b1 W
b11111 +
1%
b1 Z
b1111011 '
#1240000
0:
00
b1 !
b1 *
0<
0=
12
05
0;
1>
01
0/
18
b11100 +
0%
b1110 $
b1110 )
b1110 Y
b0 Z
b1111100 '
#1250000
1<
1:
10
b10 !
b10 *
03
14
11
b10 W
b11111 +
1%
b1 Z
b1111101 '
#1260000
04
02
15
01
1/
b11110 +
0%
b1111 $
b1111 )
b1111 Y
b0 Z
b1111110 '
#1270000
b11 !
b11 *
13
11
b11 W
b11111 +
1%
b1 Z
b1111111 '
#1280000
0L
0B
0"
0<
1E
0F
0K
0:
0C
0N
0O
00
09
b100 !
b100 *
03
0M
05
0>
01
0/
08
0A
0J
0.
07
1@
0V
b100 W
b0 +
0%
b0 $
b0 )
b100 #
b100 (
b100 X
b0 Y
b0 Z
b10000000 '
#1290000
b101 !
b101 *
13
11
b101 W
b1 +
1%
b1 Z
b10000001 '
#1300000
12
01
1/
b0 +
0%
b1 $
b1 )
b1 Y
b0 Z
b10000010 '
#1310000
1<
1:
10
b110 !
b110 *
03
14
11
b110 W
b11 +
1%
b1 Z
b10000011 '
#1320000
0N
0L
0B
1E
0F
0C
0:
09
00
b110 !
b110 *
1<
0=
04
02
1;
01
0/
18
b0 +
0%
b10 $
b10 )
b10 Y
b0 Z
b10000100 '
#1330000
b111 !
b111 *
13
11
b111 W
b1 +
1%
b1 Z
b10000101 '
#1340000
12
01
1/
b0 +
0%
b11 $
b11 )
b11 Y
b0 Z
b10000110 '
#1350000
1N
1L
1B
0E
1F
1C
19
0<
1=
1:
10
b1000 !
b1000 *
03
14
11
b1000 W
b1111 +
1%
b1 Z
b10000111 '
#1360000
0C
0:
09
00
0<
0=
b1000 !
b1000 *
0E
0F
04
02
0;
0D
1G
01
0/
08
1A
b1000 +
0%
b100 $
b100 )
b100 Y
b0 Z
b10001000 '
#1370000
b1001 !
b1001 *
13
11
b1001 W
b1001 +
1%
b1 Z
b10001001 '
#1380000
12
01
1/
b1000 +
0%
b101 $
b101 )
b101 Y
b0 Z
b10001010 '
#1390000
1<
1:
10
b1010 !
b1010 *
03
14
11
b1010 W
b1011 +
1%
b1 Z
b10001011 '
#1400000
0E
0C
0:
09
00
b1010 !
b1010 *
1<
0=
04
02
1;
01
0/
18
b1000 +
0%
b110 $
b110 )
b110 Y
b0 Z
b10001100 '
#1410000
b1011 !
b1011 *
13
11
b1011 W
b1001 +
1%
b1 Z
b10001101 '
#1420000
12
01
1/
b1000 +
0%
b111 $
b111 )
b111 Y
b0 Z
b10001110 '
#1430000
1E
1C
19
0<
1=
1:
10
b1100 !
b1100 *
03
14
11
b1100 W
b1111 +
1%
b1 Z
b10001111 '
#1440000
0C
0"
0:
09
0L
0K
00
0<
0=
1E
0F
0B
b1100 !
b1100 *
1N
0O
04
02
0;
1D
0G
1M
01
0/
08
0A
1J
b0 +
0%
b1000 $
b1000 )
b1000 Y
b0 Z
b10010000 '
#1450000
b1101 !
b1101 *
13
11
b1101 W
b1 +
1%
b1 Z
b10010001 '
#1460000
12
01
1/
b0 +
0%
b1001 $
b1001 )
b1001 Y
b0 Z
b10010010 '
#1470000
1<
1:
10
b1110 !
b1110 *
03
14
11
b1110 W
b11 +
1%
b1 Z
b10010011 '
#1480000
0"
0K
1N
0O
0L
0B
1E
0F
0C
0:
09
00
b1110 !
b1110 *
1<
0=
04
02
1;
01
0/
18
b0 +
0%
b1010 $
b1010 )
b1010 Y
b0 Z
b10010100 '
#1490000
b1111 !
b1111 *
13
11
b1111 W
b1 +
1%
b1 Z
b10010101 '
#1500000
12
01
1/
b0 +
0%
b1011 $
b1011 )
b1011 Y
b0 Z
b10010110 '
#1510000
1"
1K
0N
1O
1L
1B
0E
1F
1C
19
0<
1=
1:
10
b0 !
b0 *
03
14
11
1V
b0 W
b11111 +
1%
b1 Z
b10010111 '
#1520000
0C
0:
09
00
0<
0=
b0 !
b0 *
0E
0F
04
02
0;
0D
1G
01
0/
08
1A
b11000 +
0%
b1100 $
b1100 )
b1100 Y
b0 Z
b10011000 '
#1530000
b1 !
b1 *
13
11
b1 W
b11001 +
1%
b1 Z
b10011001 '
#1540000
12
01
1/
b11000 +
0%
b1101 $
b1101 )
b1101 Y
b0 Z
b10011010 '
#1550000
1<
1:
10
b10 !
b10 *
03
14
11
b10 W
b11011 +
1%
b1 Z
b10011011 '
#1560000
0E
0C
0:
09
00
b10 !
b10 *
1<
0=
04
02
1;
01
0/
18
b11000 +
0%
b1110 $
b1110 )
b1110 Y
b0 Z
b10011100 '
#1570000
b11 !
b11 *
13
11
b11 W
b11001 +
1%
b1 Z
b10011101 '
#1580000
12
01
1/
b11000 +
0%
b1111 $
b1111 )
b1111 Y
b0 Z
b10011110 '
#1590000
1E
1C
19
0<
1=
1:
10
b100 !
b100 *
03
14
11
b100 W
b11111 +
1%
b1 Z
b10011111 '
#1600000
0C
0"
0:
09
0L
0K
00
0<
0=
1E
0F
0B
0N
0O
b101 !
b101 *
13
04
0;
1D
0G
0M
01
0/
08
0A
0J
1.
0V
b101 W
b0 +
0%
b0 $
b0 )
b101 #
b101 (
b101 X
b0 Y
b0 Z
b10100000 '
#1610000
1<
1:
10
b110 !
b110 *
03
14
11
b110 W
b11 +
1%
b1 Z
b10100001 '
#1620000
04
02
15
01
1/
b10 +
0%
b1 $
b1 )
b1 Y
b0 Z
b10100010 '
#1630000
b111 !
b111 *
13
11
b111 W
b11 +
1%
b1 Z
b10100011 '
#1640000
0N
0L
0B
1E
0F
0C
0:
09
00
b111 !
b111 *
1<
0=
12
05
1;
01
0/
18
b0 +
0%
b10 $
b10 )
b10 Y
b0 Z
b10100100 '
#1650000
1N
1L
1B
0E
1F
1C
19
0<
1=
1:
10
b1000 !
b1000 *
03
14
11
b1000 W
b1111 +
1%
b1 Z
b10100101 '
#1660000
04
02
15
01
1/
b1110 +
0%
b11 $
b11 )
b11 Y
b0 Z
b10100110 '
#1670000
b1001 !
b1001 *
13
11
b1001 W
b1111 +
1%
b1 Z
b10100111 '
