digital_circuits/sequential_circuits/counter/synchronous_counters/up_counter/mod_8/rtl/D.v
module D (
    input clk,
    input en,
    input areset_n,
    input d,
    output reg q
);

    always @(posedge clk, negedge areset_n) begin
        if(!areset_n) begin
            q <= 1'b0;
        end
        else if(en) begin
            q <= d;
        end
        else begin
            q <= q;
        end
    end

endmodule

digital_circuits/sequential_circuits/counter/synchronous_counters/down_counter/mod_6/rtl/mod_6.v
module mod_6(
    input clk,
    input en,
    input areset_n,
    output [2:0] out
);

    wire [2:0] w;
    D dff2(
        .clk(clk),
        .en(en),
        .areset_n(areset_n),
        .d(((w[2] & w[0]) | (~w[2] & ~w[1] & ~w[0]))),
        .q(w[2])
    );
    
    D dff1(
        .clk(clk),
        .en(en),
        .areset_n(areset_n),
        .d((w[2] & ~w[0]) | (w[1] & w[0])),
        .q(w[1])
    );

    D dff0(
        .clk(clk),
        .en(en),
        .areset_n(areset_n),
        .d(~w[0]),
        .q(w[0])
    );

    assign out = w;
endmodule

digital_circuits/sequential_circuits/counter/synchronous_counters/down_counter/mod_6/tb/tb_mod_6.v
`timescale 1ns/1ps

module tb_mod_6;
    reg clk;
    reg en;
    reg areset_n;
    wire [2:0] out;

    mod_6 dut(
        .clk(clk),
        .en(en),
        .areset_n(areset_n),
        .out(out)
    );

    initial begin
        $dumpfile("waves/dump.vcd");
        $dumpvars(0,tb_mod_6);
    end

    initial begin
        clk =0;
        forever #5 clk = ~clk;
    end

    initial begin
        en=0;
        areset_n= 0;
    end

    task check;
        begin
            $display("en = %b | areset_n = %b | out = %h",en,areset_n,out);
        end
    endtask

    initial begin
        #3 en=1;
        #3 areset_n=1;
        repeat(20) begin
            @(negedge clk) check();
        end

        #20 $finish;
    end
endmodule

digital_circuits/sequential_circuits/counter/synchronous_counters/down_counter/mod_6/waves/dump.vcd
$date
	Wed Sep 16 12:00:32 2026
$end
$version
	Icarus Verilog
$end
$timescale
	1ps
$end
$scope module tb_mod_6 $end
$var wire 3 ! out [2:0] $end
$var reg 1 " areset_n $end
$var reg 1 # clk $end
$var reg 1 $ en $end
$scope module dut $end
$var wire 1 " areset_n $end
$var wire 1 # clk $end
$var wire 1 $ en $end
$var wire 3 % out [2:0] $end
$var wire 3 & w [2:0] $end
$scope module dff0 $end
$var wire 1 " areset_n $end
$var wire 1 # clk $end
$var wire 1 ' d $end
$var wire 1 $ en $end
$var reg 1 ( q $end
$upscope $end
$scope module dff1 $end
$var wire 1 " areset_n $end
$var wire 1 # clk $end
$var wire 1 ) d $end
$var wire 1 $ en $end
$var reg 1 * q $end
$upscope $end
$scope module dff2 $end
$var wire 1 " areset_n $end
$var wire 1 # clk $end
$var wire 1 + d $end
$var wire 1 $ en $end
$var reg 1 , q $end
$upscope $end
$upscope $end
$scope task check $end
$upscope $end
$upscope $end
$enddefinitions $end
$comment Show the parameter values. $end
$dumpall
$end
#0
$dumpvars
0,
1+
0*
0)
0(
1'
b0 &
b0 %
0$
0#
0"
b0 !
$end
#3000
1$
#5000
1#
#6000
1"
#10000
0#
#15000
0'
1,
b101 !
b101 %
b101 &
1(
1#
#20000
0#
#25000
1)
0+
1'
b100 !
b100 %
b100 &
0(
1#
#30000
0#
#35000
0'
0,
1*
b11 !
b11 %
b11 &
1(
1#
#40000
0#
#45000
0)
1'
b10 !
b10 %
b10 &
0(
1#
#50000
0#
#55000
0'
0*
b1 !
b1 %
b1 &
1(
1#
#60000
0#
#65000
1+
1'
b0 !
b0 %
b0 &
0(
1#
#70000
0#
#75000
0'
1,
b101 !
b101 %
b101 &
1(
1#
#80000
0#
#85000
1)
0+
1'
b100 !
b100 %
b100 &
0(
1#
#90000
0#
#95000
0'
0,
1*
b11 !
b11 %
b11 &
1(
1#
#100000
0#
#105000
0)
1'
b10 !
b10 %
b10 &
0(
1#
#110000
0#
#115000
0'
0*
b1 !
b1 %
b1 &
1(
1#
#120000
0#
#125000
1+
1'
b0 !
b0 %
b0 &
0(
1#
#130000
0#
#135000
0'
1,
b101 !
b101 %
b101 &
1(
1#
#140000
0#
#145000
1)
0+
1'
b100 !
b100 %
b100 &
0(
1#
#150000
0#
#155000
0'
0,
1*
b11 !
b11 %
b11 &
1(
1#
#160000
0#
#165000
0)
1'
b10 !
b10 %
b10 &
0(
1#
#170000
0#
#175000
0'
0*
b1 !
b1 %
b1 &
1(
1#
#180000
0#
#185000
1+
1'
b0 !
b0 %
b0 &
0(
1#
#190000
0#
#195000
0'
1,
b101 !
b101 %
b101 &
1(
1#
#200000
0#
#205000
1)
0+
1'
b100 !
b100 %
b100 &
0(
1#
#210000
0#
#215000
0'
0,
1*
b11 !
b11 %
b11 &
1(
1#
