digital_circuits/sequential_circuits/fsm/sequence_detector/s_1010/moore/s_1010_non_overlapping/rtl/s_1010_non_overlapping.v
module s_1010_non_overlapping (
    input clk,
    input en,
    input areset_n,
    input in, 
    output reg out
);

    parameter a = 3'b000;
    parameter b = 3'b001;
    parameter c = 3'b010;
    parameter d = 3'b011;
    parameter e = 3'b100;

    reg [2:0] state, next;

    always @(posedge clk, negedge areset_n) begin
        if(~areset_n) begin
            state <= a;
        end
        else begin
            if(en) begin
                state <= next;
            end
            else begin
                state <= state;
            end
        end
    end

    always @(state, in) begin
        next = a;

        case (state) 
            a: begin
                if(in) begin
                    next = b;
                end
                else begin
                    next = a;
                end
            end

            b: begin
                if(in) begin
                    next = b;
                end
                else begin
                    next = c;
                end
            end

            c: begin
                if(in) begin
                    next = d;
                end
                else begin
                    next = a;
                end
            end

            d: begin
                if(in) begin
                    next = b;
                end
                else begin
                    next = e;
                end
            end

            e: begin
                if(in) begin
                    next = b;
                end
                else begin
                    next = a;
                end
            end
        endcase
    end

    always @(state) begin
        out = 0;
        if (state == e) begin
            out = 1;
        end
        else begin
            out = 0;
        end
    end

endmodule

digital_circuits/sequential_circuits/fsm/sequence_detector/s_1010/mealy/s_1010_non_overlapping/tb/tb_s_1010_non_overlapping.v
`timescale 1ns/1ps

module tb_s_1010_non_overlapping;
    reg clk;
    reg en;
    reg areset_n;
    reg in;
    wire out;

    s_1010_non_overlapping dut (
        .clk(clk),
        .en(en),
        .areset_n(areset_n),
        .in(in),
        .out(out)
    );

    initial begin
        $dumpfile("waves/dump.vcd");
        $dumpvars(0,tb_s_1010_non_overlapping);
    end

    initial begin
        clk = 0;
        en =0;
        areset_n =0;
        in = 0;
        forever #5 clk = ~clk;
    end

    task check;
        input reg t_in;
        begin
            in = t_in;
            #1;
            $display("en = %b | areset_n = %b | in = %b | out = %b",en,areset_n,in,out);
        end
    endtask

    initial begin
        #3 en = 1;
        #3 areset_n = 1;
        @(negedge clk) check(0);
        @(negedge clk) check(0);
        @(negedge clk) check(1);
        @(negedge clk) check(0);
        @(negedge clk) check(1);
        @(negedge clk) check(0);
        @(negedge clk) check(1);
        @(negedge clk) check(0);
        @(negedge clk) check(1);
        @(negedge clk) check(1);
        @(negedge clk) check(0);
        @(negedge clk) check(1);
        @(negedge clk) check(0);


        #10; $finish;
    end
endmodule

digital_circuits/sequential_circuits/fsm/sequence_detector/s_1010/moore/s_1010_non_overlapping/waves/dump.vcd
$date
	Thu Sep 17 09:13:25 2026
$end
$version
	Icarus Verilog
$end
$timescale
	1ps
$end
$scope module tb_s_1010_non_overlapping $end
$var wire 1 ! out $end
$var reg 1 " areset_n $end
$var reg 1 # clk $end
$var reg 1 $ en $end
$var reg 1 % in $end
$scope module dut $end
$var wire 1 " areset_n $end
$var wire 1 # clk $end
$var wire 1 $ en $end
$var wire 1 % in $end
$var parameter 3 & a $end
$var parameter 3 ' b $end
$var parameter 3 ( c $end
$var parameter 3 ) d $end
$var parameter 3 * e $end
$var reg 3 + next [2:0] $end
$var reg 1 ! out $end
$var reg 3 , state [2:0] $end
$upscope $end
$scope task check $end
$var reg 1 - t_in $end
$upscope $end
$upscope $end
$enddefinitions $end
$comment Show the parameter values. $end
$dumpall
b100 *
b11 )
b10 (
b1 '
b0 &
$end
#0
$dumpvars
x-
b0 ,
b0 +
0%
0$
0#
0"
0!
$end
#3000
1$
#5000
1#
#6000
1"
#10000
0-
0#
#15000
1#
#20000
0#
#25000
1#
#30000
b1 +
1%
1-
0#
#35000
b1 +
b1 ,
1#
#40000
b10 +
0%
0-
0#
#45000
b0 +
b10 ,
1#
#50000
b11 +
1%
1-
0#
#55000
b1 +
b11 ,
1#
#60000
b100 +
0%
0-
0#
#65000
1!
b0 +
b100 ,
1#
#70000
b1 +
1%
1-
0#
#75000
0!
b1 +
b1 ,
1#
#80000
b10 +
0%
0-
0#
#85000
b0 +
b10 ,
1#
#90000
b11 +
1%
1-
0#
#95000
b1 +
b11 ,
1#
#100000
0#
#105000
b1 +
b1 ,
1#
#110000
b10 +
0%
0-
0#
#115000
b0 +
b10 ,
1#
#120000
b11 +
1%
1-
0#
#125000
b1 +
b11 ,
1#
#130000
b100 +
0%
0-
0#
#135000
1!
b0 +
b100 ,
1#
